Workbook

Sheet 00 Legenda
A1: Indici clinici - aggregazione multi-articolo, calcolo e valutazione della pericolosita
A2: Fonti integrate: Art.1 cardiologici, Art.2 antropometrici, Art.3 profilo marziale, Art.4 indici infiammatori. Stesso soggetto dimostrativo.
A5: SCOPO | B5: Raccogliere in un unico modello formule e indici estratti dagli articoli forniti, ricalcolarli in modo trasparente dai dati grezzi del soggetto, verificare la riproducibilita dei valori pubblicati e produrre una valutazione strutturata del livello di pericolosita.
A7: AVVERTENZA | B7: Strumento didattico e di sintesi documentale. NON e un dispositivo medico e non produce diagnosi. 'Gennarino Parsifallo' e dichiarato dalla fonte stessa come caso dimostrativo, non un paziente reale. Ogni decisione clinica compete al medico.
A9: COME SI USA | B9: 1) Apri '01 Input' e modifica SOLO le celle blu su sfondo giallo. 2) Tutti gli altri fogli si ricalcolano da soli. 3) '02 Indici' contiene i 59 indici delle quattro fonti, ricalcolati e confrontati con il referto. 4) '06 Rischio' produce il punteggio complessivo di pericolosita. 5) '08 Controlli' elenca cosa e riproducibile e cosa no: leggilo prima di fidarti dei numeri.
A11: CONVENZIONI COLORE
A12: Testo blu su giallo | B12: Dato inserito a mano. E l'unica cosa da modificare.
A13: Testo nero | B13: Risultato calcolato nel foglio stesso.
A14: Testo verde | B14: Valore richiamato da un altro foglio.
A15: Riga arancione | B15: Indice fuori intervallo nella direzione critica.
A16: Riga gialla | B16: Indice dentro l'intervallo ma in zona di guardia.
A18: FOGLI
A19: 01 Input | B19: Dati grezzi del soggetto, laboratorio e fattori anamnestici. Unico foglio da compilare.
A20: 02 Indici | B20: I 59 indici delle quattro fonti: formula, valore ricalcolato, scostamento dal referto, intervallo di riferimento, stato, peso clinico e punteggio.
A21: 03 Formule | B21: Dizionario delle formule con derivazione e verifica numerica.
A22: 04 Zone FC | B22: Zone di frequenza cardiaca ricavate dalla frequenza massima.
A23: 05 Evidenze | B23: Letteratura citata dalle due fonti con PMID e applicabilita al caso.
A24: 06 Rischio | B24: Motore di calcolo: punteggio strumentale per fonte, fattori anamnestici, rischio relativo epidemiologico e indice composito di pericolosita.
A25: 07 Scenari | B25: Simulazioni what-if sugli interventi discussi dalle fonti.
A26: 08 Controlli | B26: Verifica di riproducibilita: quali valori pubblicati si riottengono dai dati grezzi e quali no.
A27: 09 Conversioni | B27: Il profilo marziale tradotto dalle unita SI a quelle di un referto di laboratorio ordinario.
A29: NOTA IMPORTANTE | B29: Il foglio '08 Controlli' registra gli scostamenti fra i valori pubblicati e il ricalcolo. I due piu rilevanti: un BMI che non discende dal peso e dall'altezza dichiarati e che si propaga su tre indici derivati, e una diagnosi di sarcopenia che poggia su una correzione di cinque millimetri la cui formula non e pubblicata. Il modello mantiene sia il valore pubblicato sia quello ricalcolato, senza sceglierne uno.
A31: AGGIUNGERE UN ARTICOLO | B31: Aggiungi le righe in fondo alle tabelle di '02 Indici', '03 Formule' e '05 Evidenze' compilando la colonna 'Fonte' con l'etichetta del nuovo articolo. Se introduce dati grezzi nuovi, inseriscili prima in '01 Input'. I conteggi di '06 Rischio' usano COUNTIFS sull'etichetta della fonte, quindi si aggiornano da soli.

Sheet 01 Input
A1: 01 - Dati grezzi del soggetto
A2: Modifica solo le celle blu su sfondo giallo. Tutto il resto del workbook si ricalcola.
A4: Parametro | B4: Valore | C4: Unita | D4: Fonte / Nota
A5: ANAGRAFICA
A6: Identificativo soggetto | B6: Gennarino Parsifallo | D6: Caso dimostrativo dichiarato dalle fonti
A7: Eta | B7: 50 | C7: anni | D7: Art.1 - Indici cardiologici / Art.2 - Indici antropometrici
A8: Sesso | B8: M | C8: M/F | D8: Determina il modello di FC massima, la stima del grasso corporeo e la formula del VAI
A10: MISURE ANTROPOMETRICHE
A11: Peso | B11: 74 | C11: kg | D11: Art.2 - Indici antropometrici
A12: Altezza | B12: 174 | C12: cm | D12: Art.2 - Indici antropometrici
A13: Circonferenza vita | B13: 97 | C13: cm | D13: Art.2 - Indici antropometrici - a fine espirazione, a meta fra ultima costa e cresta iliaca. Alimenta nove dei dodici indici antropometrici
A14: Circonferenza fianchi | B14: 100 | C14: cm | D14: Art.2 - Indici antropometrici
A15: Circonferenza polpaccio | B15: 34 | C15: cm | D15: Art.2 - Indici antropometrici - surrogato validato della massa muscolare appendicolare (PMID 30312372)
A16: Circonferenza polso | B16: 18 | C16: cm | D16: Art.2 - Indici antropometrici - misura stabile per tutta la vita adulta: e il riferimento fisso del morfotipo
A17: Peso all'eta di 30 anni | B17: 68 | C17: kg | D17: Art.2 - Indici antropometrici - serve a calcolare l'incremento ponderale ventennale
A18: Superficie corporea (BSA) | B18: 1.9 | C18: m2 | D18: Art.1 - Indici cardiologici - riportata come 'circa 1,9 m2'; denominatore degli indici cardiologici indicizzati
A20: MISURE CARDIOVASCOLARI
A21: Pressione sistolica (SBP) | B21: 128 | C21: mmHg | D21: Art.1 - Indici cardiologici
A22: Pressione diastolica (DBP) | B22: 84 | C22: mmHg | D22: Art.1 - Indici cardiologici
A23: Frequenza cardiaca a riposo (FC) | B23: 82 | C23: bpm | D23: Art.1 - Indici cardiologici - unico indice cardiologico fuori range del referto
A24: Gittata sistolica (SV) | B24: 66 | C24: mL | D24: Art.1 - Indici cardiologici
A25: Frequenza cardiaca massima da referto | B25: 175 | C25: bpm | D25: Art.1 - Indici cardiologici - modello logistico sesso-specifico (PMID 12752560 / 11722475); i coefficienti non sono pubblicati, quindi il valore si inserisce a mano
A26: Pressione venosa centrale assunta (CVP) | B26: 5 | C26: mmHg | D26: ASSUNZIONE: non riportata dalle fonti. Serve solo alle resistenze vascolari. Con CVP=5 il calcolo restituisce i 2,7 kU*m2 del referto
A28: LABORATORIO
A29: Colesterolo HDL | B29: 41 | C29: mg/dL | D29: Art.2 - Indici antropometrici - preso da solo nessun laboratorio lo segnalerebbe. Alimenta CMI e VAI
A30: Trigliceridi | B30: 148 | C30: mg/dL | D30: Art.2 - Indici antropometrici - idem. Alimenta LAP, CMI e VAI
A32: PROFILO MARZIALE (valori misurati)
A33: Sideremia | B33: 13.6 | C33: uM | D33: Art.3 - Profilo marziale - ritmo circadiano marcato: il prelievo va fatto al mattino a digiuno, altrimenti la saturazione risulta abbassata di diversi punti senza che le riserve siano cambiate
A34: Transferrina | B34: 39.2 | C34: uM | D34: Art.3 - Profilo marziale - il fegato ne produce di piu proprio quando il ferro scarseggia. Da qui derivano TIBC e UIBC
A35: Ferritina | B35: 160.9 | C35: pM | D35: Art.3 - Profilo marziale - proteina di fase acuta positiva: sale con l'infiammazione a prescindere da quanto ferro contenga
A36: Fattore di aggiustamento BRINDA - sideremia | B36: 1.2574 | C36: - | D36: DEDOTTO: rapporto fra il valore aggiustato e quello grezzo pubblicati (17,1/13,6). I marcatori di infiammazione su cui si basa la correzione non sono riportati dall'articolo
A37: Fattore di aggiustamento BRINDA - ferritina | B37: 0.7502 | C37: - | D37: DEDOTTO: rapporto fra il valore aggiustato e quello grezzo pubblicati (120,7/160,9). Corrisponde a una riduzione del 25% esatto
A39: INFIAMMAZIONE - misure dirette
A40: Proteina C reattiva (PCR) | B40: 0.3 | C40: mg/dL | D40: Art.4 - Indici infiammatori - proteina di fase acuta: sale molto e in fretta nell'infiammazione acuta, ed e per questo un cattivo strumento per quella cronica di basso grado
A41: VES a 1 ora | B41: 14 | C41: mm | D41: Art.4 - Indici infiammatori - misura una proprieta reologica del sangue che cambia nell'arco di giorni
A42: Omocisteina | B42: 14.6 | C42: uM | D42: Art.4 - Indici infiammatori
A43: Uricemia | B43: 6.7 | C43: mg/dL | D43: Art.4 - Indici infiammatori
A45: EMOCROMO - valori ricostruiti per inversione degli indici
A46: Piastrine | B46: 272 | C46: 10^9/L | D46: DEDOTTO da AISI/SIRI. L'articolo non pubblica l'emocromo assoluto: i valori di questa sezione sono stati ricavati invertendo gli indici derivati
A47: Linfociti | B47: 1.7407 | C47: 10^9/L | D47: DEDOTTO da (AISI/SII)/MLR
A48: Neutrofili | B48: 5.8684 | C48: 10^9/L | D48: DEDOTTO da SIRI x linfociti / monociti. In percentuale l'articolo cita 69%, con limite a 70
A49: Monociti | B49: 0.6615 | C49: 10^9/L | D49: DEDOTTO da AISI/SII. Corrisponde a circa il 7,8% della formula leucocitaria
A50: Volume piastrinico medio (MPV) | B50: 11.906 | C50: fL | D50: DEDOTTO da (MPV/linfociti) x linfociti
A51: Ampiezza di distribuzione eritrocitaria (RDW) | B51: 14.5 | C51: % | D51: ASSUNTO: il sistema e sottodeterminato. RDW/Piastrine e pubblicato con due sole cifre decimali (0,05), compatibile con un RDW fra 12,2 e 15,0. Scelto 14,5 perche coerente con l'anemia lieve descritta dalla serie
A52: Emoglobina | B52: 13.9 | C52: g/dL | D52: ASSUNTO: discende dall'RDW scelto tramite il rapporto Emoglobina/RDW pubblicato (0,96)
A54: VALORI NON RICALCOLABILI (inseriti dal referto)
A55: ABSI z-score da referto | B55: 1.52 | C55: z | D55: Art.2 - Indici antropometrici - il valore grezzo di ABSI e ricalcolabile, ma lo z-score richiede le tabelle NHANES per eta e sesso, che non sono pubblicate. Vedi foglio 08
A57: FATTORI ANAMNESTICI (0 = assente, 1 = presente)
A58: Sigarette al giorno | B58: 20 | C58: n/die | D58: Art.1 - Indici cardiologici / Art.2 - Indici antropometrici
A59: Anni di abitudine tabagica | B59: 30 | C59: anni | D59: Art.1 - Indici cardiologici / Art.2 - Indici antropometrici
A60: Miosteatosi documentata | B60: 1 | C60: 0/1 | D60: Art.2 - Indici antropometrici - infiltrazione adiposa del muscolo; non misurabile con l'antropometria di superficie
A61: Sospetta apnea ostruttiva del sonno mai indagata | B61: 1 | C61: 0/1 | D61: Russamento e pause respiratorie riferite dalla convivente, nessun accertamento eseguito
A62: Sedentarieta / assenza di esercizio strutturato | B62: 1 | C62: 0/1 | D62: Art.2 - Indici antropometrici - calcetto interrotto a 40 anni e mai ripreso, 30.000 km l'anno in auto
A64: PARAMETRI DI CONFRONTO E SOGLIE
A65: FC a riposo di riferimento ottimale | B65: 65 | C65: bpm | D65: Punto medio della fascia 60-69 bpm, minimo di mortalita (PMID 11337213)
A66: Soglia FC a riposo ad alto rischio | B66: 80 | C66: bpm | D66: Soglia oltre la quale il rischio cambia scala (PMID 26598376, PMID 28067310)
A67: Limite superiore FC del referto | B67: 76 | C67: bpm | D67: Estremo alto dell'intervallo del referto; base del calcolo dei battiti in eccesso
A68: Soglia vita per sindrome metabolica (maschio europeo) | B68: 101 | C68: cm | D68: Art.2 - Indici antropometrici - criterio antropometrico; il soggetto ne misura 97 e la casella resta vuota

Sheet 02 Indici
A1: 02 - Indici estratti dalle fonti, ricalcolati e valutati
A2: Colonna E ricalcolata dai dati grezzi del foglio 01. Colonna G riporta il valore pubblicato: la colonna H rende visibile ogni scostamento.
A4: # | B4: Gruppo | C4: Indice | D4: Formula | E4: Valore calcolato | F4: Unita | G4: Valore referto | H4: Scost. % | I4: Rif. min | J4: Rif. max | K4: Direzione critica | L4: Posiz. range | M4: Stato | N4: Peso | O4: Punt. 0-3 | P4: Contrib. | Q4: Fonte | R4: Note e interpretazione
A5: 1 | B5: Pressori | C5: Pressione sistolica | D5: misurata | E5: ='01 Input'!$B$21 -> 128 | F5: mmHg | G5: 128 | H5: =IF(G5=0,"",(E5-G5)/ABS(G5)) -> 0 | I5: 100 | J5: 129 | K5: Alto | L5: =IF(J5=I5,"",(E5-I5)/(J5-I5)) -> 0.96551724 | M5: =IF(E5>J5,"Fuori (alto)",IF(E5<I5,"Fuori (basso)",IF(AND(K5<>"Informativo",OR(AND(OR(K5="Alto",K5="Bilaterale"),L5>0.8),AND(OR(K5="Basso",K5="Bilaterale"),L5<0.2))),"Borderline","Normale"))) -> Borderline | N5: 1 | O5: =IF(N5=0,0,IF(AND(E5>J5,OR(K5="Alto",K5="Bilaterale")),IF((E5-J5)/(J5-I5)>0.1,3,2),IF(AND(E5<I5,OR(K5="Basso",K5="Bilaterale")),IF((I5-E5)/(J5-I5)>0.1,3,2),IF(M5="Borderline",1,0)))) -> 1 | P5: =N5*O5 -> 1 | Q5: Art.1 - Indici cardiologici | R5: Dentro l'intervallo ma a 1 mmHg dal limite superiore.
A6: 2 | B6: Pressori | C6: Pressione diastolica | D6: misurata | E6: ='01 Input'!$B$22 -> 84 | F6: mmHg | G6: 84 | H6: =IF(G6=0,"",(E6-G6)/ABS(G6)) -> 0 | I6: 60 | J6: 84 | K6: Alto | L6: =IF(J6=I6,"",(E6-I6)/(J6-I6)) -> 1 | M6: =IF(E6>J6,"Fuori (alto)",IF(E6<I6,"Fuori (basso)",IF(AND(K6<>"Informativo",OR(AND(OR(K6="Alto",K6="Bilaterale"),L6>0.8),AND(OR(K6="Basso",K6="Bilaterale"),L6<0.2))),"Borderline","Normale"))) -> Borderline | N6: 1 | O6: =IF(N6=0,0,IF(AND(E6>J6,OR(K6="Alto",K6="Bilaterale")),IF((E6-J6)/(J6-I6)>0.1,3,2),IF(AND(E6<I6,OR(K6="Basso",K6="Bilaterale")),IF((I6-E6)/(J6-I6)>0.1,3,2),IF(M6="Borderline",1,0)))) -> 1 | P6: =N6*O6 -> 1 | Q6: Art.1 - Indici cardiologici | R6: Esattamente sul limite superiore. La fonte segnala che la soglia contera quando entrera in uno score.
A7: 3 | B7: Pressori | C7: Pressione arteriosa media (MAP) | D7: DBP + 0,4 x PP | E7: =E6+0.4*E8 -> 101.6 | F7: mmHg | G7: 101 | H7: =IF(G7=0,"",(E7-G7)/ABS(G7)) -> 0.0059405941 | I7: 70 | J7: 105 | K7: Alto | L7: =IF(J7=I7,"",(E7-I7)/(J7-I7)) -> 0.90285714 | M7: =IF(E7>J7,"Fuori (alto)",IF(E7<I7,"Fuori (basso)",IF(AND(K7<>"Informativo",OR(AND(OR(K7="Alto",K7="Bilaterale"),L7>0.8),AND(OR(K7="Basso",K7="Bilaterale"),L7<0.2))),"Borderline","Normale"))) -> Borderline | N7: 1 | O7: =IF(N7=0,0,IF(AND(E7>J7,OR(K7="Alto",K7="Bilaterale")),IF((E7-J7)/(J7-I7)>0.1,3,2),IF(AND(E7<I7,OR(K7="Basso",K7="Bilaterale")),IF((I7-E7)/(J7-I7)>0.1,3,2),IF(M7="Borderline",1,0)))) -> 1 | P7: =N7*O7 -> 1 | Q7: Art.1 - Indici cardiologici | R7: La MAP classica (SBP+2xDBP)/3 darebbe 98,7 e non 101: il valore pubblicato si riproduce solo con DBP + 0,4 x PP. La scelta si propaga sul Modified Shock Index, che ha la MAP al denominatore.
A8: 4 | B8: Pressori | C8: Pressione di pulsazione (PP) | D8: SBP - DBP | E8: =E5-E6 -> 44 | F8: mmHg | G8: 44 | H8: =IF(G8=0,"",(E8-G8)/ABS(G8)) -> 0 | I8: 30 | J8: 55 | K8: Alto | L8: =IF(J8=I8,"",(E8-I8)/(J8-I8)) -> 0.56 | M8: =IF(E8>J8,"Fuori (alto)",IF(E8<I8,"Fuori (basso)",IF(AND(K8<>"Informativo",OR(AND(OR(K8="Alto",K8="Bilaterale"),L8>0.8),AND(OR(K8="Basso",K8="Bilaterale"),L8<0.2))),"Borderline","Normale"))) -> Normale | N8: 2 | O8: =IF(N8=0,0,IF(AND(E8>J8,OR(K8="Alto",K8="Bilaterale")),IF((E8-J8)/(J8-I8)>0.1,3,2),IF(AND(E8<I8,OR(K8="Basso",K8="Bilaterale")),IF((I8-E8)/(J8-I8)>0.1,3,2),IF(M8="Borderline",1,0)))) -> 0 | P8: =N8*O8 -> 0 | Q8: Art.1 - Indici cardiologici | R8: Marcatore di elasticita dei grossi vasi e di invecchiamento vascolare (PMID 33793325). Dentro il range: da sorvegliare, non da segnalare.
A9: 5 | B9: Dinamici | C9: Frequenza cardiaca a riposo | D9: misurata | E9: ='01 Input'!$B$23 -> 82 | F9: bpm | G9: 82 | H9: =IF(G9=0,"",(E9-G9)/ABS(G9)) -> 0 | I9: 72 | J9: 76 | K9: Alto | L9: =IF(J9=I9,"",(E9-I9)/(J9-I9)) -> 2.5 | M9: =IF(E9>J9,"Fuori (alto)",IF(E9<I9,"Fuori (basso)",IF(AND(K9<>"Informativo",OR(AND(OR(K9="Alto",K9="Bilaterale"),L9>0.8),AND(OR(K9="Basso",K9="Bilaterale"),L9<0.2))),"Borderline","Normale"))) -> Fuori (alto) | N9: 3 | O9: =IF(N9=0,0,IF(AND(E9>J9,OR(K9="Alto",K9="Bilaterale")),IF((E9-J9)/(J9-I9)>0.1,3,2),IF(AND(E9<I9,OR(K9="Basso",K9="Bilaterale")),IF((I9-E9)/(J9-I9)>0.1,3,2),IF(M9="Borderline",1,0)))) -> 3 | P9: =N9*O9 -> 9 | Q9: Art.1 - Indici cardiologici | R9: Unico indice cardiologico fuori range, liquidato come 'tachicardia lieve'. E anche quello con il supporto epidemiologico piu solido, ed e il motore aritmetico di meta degli altri indici della sezione.
A10: 6 | B10: Dinamici | C10: Frequenza cardiaca massima stimata | D10: modello logistico sesso-specifico | E10: ='01 Input'!$B$25 -> 175 | F10: bpm | G10: 175 | H10: =IF(G10=0,"",(E10-G10)/ABS(G10)) -> 0 | I10: 158 | J10: 192 | K10: Informativo | L10: =IF(J10=I10,"",(E10-I10)/(J10-I10)) -> 0.5 | M10: =IF(E10>J10,"Fuori (alto)",IF(E10<I10,"Fuori (basso)",IF(AND(K10<>"Informativo",OR(AND(OR(K10="Alto",K10="Bilaterale"),L10>0.8),AND(OR(K10="Basso",K10="Bilaterale"),L10<0.2))),"Borderline","Normale"))) -> Normale | N10: 0 | O10: =IF(N10=0,0,IF(AND(E10>J10,OR(K10="Alto",K10="Bilaterale")),IF((E10-J10)/(J10-I10)>0.1,3,2),IF(AND(E10<I10,OR(K10="Basso",K10="Bilaterale")),IF((I10-E10)/(J10-I10)>0.1,3,2),IF(M10="Borderline",1,0)))) -> 0 | P10: =N10*O10 -> 0 | Q10: Art.1 - Indici cardiologici | R10: Stima anagrafica, non misura: non descrive lo stato del soggetto, quindi peso 0. L'intervallo 158-192 e il 90-110% del predetto. Confronto con 220-eta (170) e Tanaka (173) nel foglio 03.
A11: 7 | B11: Dinamici | C11: Frequenza cardiaca di riserva | D11: FC max - FC riposo | E11: =E10-E9 -> 93 | F11: bpm | G11: 93 | H11: =IF(G11=0,"",(E11-G11)/ABS(G11)) -> 0 | I11: 70 | J11: 120 | K11: Basso | L11: =IF(J11=I11,"",(E11-I11)/(J11-I11)) -> 0.46 | M11: =IF(E11>J11,"Fuori (alto)",IF(E11<I11,"Fuori (basso)",IF(AND(K11<>"Informativo",OR(AND(OR(K11="Alto",K11="Bilaterale"),L11>0.8),AND(OR(K11="Basso",K11="Bilaterale"),L11<0.2))),"Borderline","Normale"))) -> Normale | N11: 1 | O11: =IF(N11=0,0,IF(AND(E11>J11,OR(K11="Alto",K11="Bilaterale")),IF((E11-J11)/(J11-I11)>0.1,3,2),IF(AND(E11<I11,OR(K11="Basso",K11="Bilaterale")),IF((I11-E11)/(J11-I11)>0.1,3,2),IF(M11="Borderline",1,0)))) -> 0 | P11: =N11*O11 -> 0 | Q11: Art.1 - Indici cardiologici | R11: Formalmente normale, ma alta perche la FC massima e alta per eta, non perche il basale sia buono. Con basale 72 salirebbe a 103 senza alcun miglioramento reale. HR 2,8 per mortalita CV in chi non impegna l'80% della riserva (PMID 17446799).
A12: 8 | B12: Dinamici | C12: Modified Shock Index (MSI) | D12: FC riposo / MAP | E12: =E9/E7 -> 0.80708661 | F12: - | G12: 0.81 | H12: =IF(G12=0,"",(E12-G12)/ABS(G12)) -> -0.0035967726 | I12: 0.7 | J12: 0.99 | K12: Alto | L12: =IF(J12=I12,"",(E12-I12)/(J12-I12)) -> 0.36926419 | M12: =IF(E12>J12,"Fuori (alto)",IF(E12<I12,"Fuori (basso)",IF(AND(K12<>"Informativo",OR(AND(OR(K12="Alto",K12="Bilaterale"),L12>0.8),AND(OR(K12="Basso",K12="Bilaterale"),L12<0.2))),"Borderline","Normale"))) -> Normale | N12: 1 | O12: =IF(N12=0,0,IF(AND(E12>J12,OR(K12="Alto",K12="Bilaterale")),IF((E12-J12)/(J12-I12)>0.1,3,2),IF(AND(E12<I12,OR(K12="Basso",K12="Bilaterale")),IF((I12-E12)/(J12-I12)>0.1,3,2),IF(M12="Borderline",1,0)))) -> 0 | P12: =N12*O12 -> 0 | Q12: Art.1 - Indici cardiologici | R12: Va calcolato sulla pressione MEDIA, non sulla sistolica: con la sistolica verrebbe 0,64, errore diffuso nei calcolatori online.
A13: 9 | B13: Dinamici | C13: Prodotto cardiovascolare (RPP) | D13: FC riposo x SBP | E13: =E9*E5 -> 10496 | F13: bpm*mmHg | G13: 10496 | H13: =IF(G13=0,"",(E13-G13)/ABS(G13)) -> 0 | I13: 10000 | J13: 14999 | K13: Alto | L13: =IF(J13=I13,"",(E13-I13)/(J13-I13)) -> 0.099219844 | M13: =IF(E13>J13,"Fuori (alto)",IF(E13<I13,"Fuori (basso)",IF(AND(K13<>"Informativo",OR(AND(OR(K13="Alto",K13="Bilaterale"),L13>0.8),AND(OR(K13="Basso",K13="Bilaterale"),L13<0.2))),"Borderline","Normale"))) -> Normale | N13: 2 | O13: =IF(N13=0,0,IF(AND(E13>J13,OR(K13="Alto",K13="Bilaterale")),IF((E13-J13)/(J13-I13)>0.1,3,2),IF(AND(E13<I13,OR(K13="Basso",K13="Bilaterale")),IF((I13-E13)/(J13-I13)>0.1,3,2),IF(M13="Borderline",1,0)))) -> 0 | P13: =N13*O13 -> 0 | Q13: Art.1 - Indici cardiologici | R13: Surrogato non invasivo del consumo miocardico di ossigeno (PMID 38453019). Il soggetto e entrato nella fascia per 496 punti, spinto dalla frequenza. Tre mesi di esercizio supervisionato lo abbassano del 19% (PMID 15793048).
A14: 10 | B14: Pompa | C14: Gittata sistolica (SV) | D14: misurata | E14: ='01 Input'!$B$24 -> 66 | F14: mL | G14: 66 | H14: =IF(G14=0,"",(E14-G14)/ABS(G14)) -> 0 | I14: 60 | J14: 100 | K14: Basso | L14: =IF(J14=I14,"",(E14-I14)/(J14-I14)) -> 0.15 | M14: =IF(E14>J14,"Fuori (alto)",IF(E14<I14,"Fuori (basso)",IF(AND(K14<>"Informativo",OR(AND(OR(K14="Alto",K14="Bilaterale"),L14>0.8),AND(OR(K14="Basso",K14="Bilaterale"),L14<0.2))),"Borderline","Normale"))) -> Borderline | N14: 2 | O14: =IF(N14=0,0,IF(AND(E14>J14,OR(K14="Alto",K14="Bilaterale")),IF((E14-J14)/(J14-I14)>0.1,3,2),IF(AND(E14<I14,OR(K14="Basso",K14="Bilaterale")),IF((I14-E14)/(J14-I14)>0.1,3,2),IF(M14="Borderline",1,0)))) -> 1 | P14: =N14*O14 -> 2 | Q14: Art.1 - Indici cardiologici | R14: Nel 15% piu basso dell'intervallo: e la pompa poco capiente che obbliga il cuore a compensare con la frequenza. E l'indice che spiega perche gli 82 battiti esistono.
A15: 11 | B15: Pompa | C15: Portata cardiaca (CO) | D15: SV x FC / 1000 | E15: =E14*E9/1000 -> 5.412 | F15: L/min | G15: 5.4 | H15: =IF(G15=0,"",(E15-G15)/ABS(G15)) -> 0.0022222222 | I15: 3.5 | J15: 6.9 | K15: Basso | L15: =IF(J15=I15,"",(E15-I15)/(J15-I15)) -> 0.56235294 | M15: =IF(E15>J15,"Fuori (alto)",IF(E15<I15,"Fuori (basso)",IF(AND(K15<>"Informativo",OR(AND(OR(K15="Alto",K15="Bilaterale"),L15>0.8),AND(OR(K15="Basso",K15="Bilaterale"),L15<0.2))),"Borderline","Normale"))) -> Normale | N15: 1 | O15: =IF(N15=0,0,IF(AND(E15>J15,OR(K15="Alto",K15="Bilaterale")),IF((E15-J15)/(J15-I15)>0.1,3,2),IF(AND(E15<I15,OR(K15="Basso",K15="Bilaterale")),IF((I15-E15)/(J15-I15)>0.1,3,2),IF(M15="Borderline",1,0)))) -> 0 | P15: =N15*O15 -> 0 | Q15: Art.1 - Indici cardiologici | R15: Il risultato finale e adeguato, ed e per questo che il referto scrive 'normale'. Lo stesso valore si ottiene con SV 80 mL e 68 bpm: identico output, meccanismo diverso.
A16: 12 | B16: Pompa | C16: Cardiac Index (CI) | D16: CO / BSA | E16: =E15/'01 Input'!$B$18 -> 2.8484211 | F16: L/min/m2 | G16: 2.8 | H16: =IF(G16=0,"",(E16-G16)/ABS(G16)) -> 0.017293233 | I16: 2.5 | J16: 3.9 | K16: Basso | L16: =IF(J16=I16,"",(E16-I16)/(J16-I16)) -> 0.24887218 | M16: =IF(E16>J16,"Fuori (alto)",IF(E16<I16,"Fuori (basso)",IF(AND(K16<>"Informativo",OR(AND(OR(K16="Alto",K16="Bilaterale"),L16>0.8),AND(OR(K16="Basso",K16="Bilaterale"),L16<0.2))),"Borderline","Normale"))) -> Normale | N16: 1 | O16: =IF(N16=0,0,IF(AND(E16>J16,OR(K16="Alto",K16="Bilaterale")),IF((E16-J16)/(J16-I16)>0.1,3,2),IF(AND(E16<I16,OR(K16="Basso",K16="Bilaterale")),IF((I16-E16)/(J16-I16)>0.1,3,2),IF(M16="Borderline",1,0)))) -> 0 | P16: =N16*O16 -> 0 | Q16: Art.1 - Indici cardiologici | R16: Portata indicizzata per superficie corporea. Nel terzo inferiore dell'intervallo.
A17: 13 | B17: Pompa | C17: Left Cardiac Work Index (LCWI) | D17: CI x MAP x 2,222 | E17: =E16*E7*2.222 -> 643.04586 | F17: mW/m2 | G17: 627 | H17: =IF(G17=0,"",(E17-G17)/ABS(G17)) -> 0.02559149 | I17: 400 | J17: 900 | K17: Bilaterale | L17: =IF(J17=I17,"",(E17-I17)/(J17-I17)) -> 0.48609173 | M17: =IF(E17>J17,"Fuori (alto)",IF(E17<I17,"Fuori (basso)",IF(AND(K17<>"Informativo",OR(AND(OR(K17="Alto",K17="Bilaterale"),L17>0.8),AND(OR(K17="Basso",K17="Bilaterale"),L17<0.2))),"Borderline","Normale"))) -> Normale | N17: 1 | O17: =IF(N17=0,0,IF(AND(E17>J17,OR(K17="Alto",K17="Bilaterale")),IF((E17-J17)/(J17-I17)>0.1,3,2),IF(AND(E17<I17,OR(K17="Basso",K17="Bilaterale")),IF((I17-E17)/(J17-I17)>0.1,3,2),IF(M17="Borderline",1,0)))) -> 0 | P17: =N17*O17 -> 0 | Q17: Art.1 - Indici cardiologici | R17: La costante 2,222 converte L/min x mmHg in milliwatt (1 L/min = 1,667e-5 m3/s; 1 mmHg = 133,322 Pa). Ricalcolando con il CI e la MAP non arrotondati si ottengono 643 contro i 627 pubblicati: differenza di solo arrotondamento.
A18: 14 | B18: Pompa | C18: Indice di rigidita arteriosa | D18: PP / MAP | E18: =E8/E7 -> 0.43307087 | F18: - | G18: 0.44 | H18: =IF(G18=0,"",(E18-G18)/ABS(G18)) -> -0.015748031 | I18: 0.3 | J18: 0.55 | K18: Alto | L18: =IF(J18=I18,"",(E18-I18)/(J18-I18)) -> 0.53228346 | M18: =IF(E18>J18,"Fuori (alto)",IF(E18<I18,"Fuori (basso)",IF(AND(K18<>"Informativo",OR(AND(OR(K18="Alto",K18="Bilaterale"),L18>0.8),AND(OR(K18="Basso",K18="Bilaterale"),L18<0.2))),"Borderline","Normale"))) -> Normale | N18: 2 | O18: =IF(N18=0,0,IF(AND(E18>J18,OR(K18="Alto",K18="Bilaterale")),IF((E18-J18)/(J18-I18)>0.1,3,2),IF(AND(E18<I18,OR(K18="Basso",K18="Bilaterale")),IF((I18-E18)/(J18-I18)>0.1,3,2),IF(M18="Borderline",1,0)))) -> 0 | P18: =N18*O18 -> 0 | Q18: Art.1 - Indici cardiologici | R18: Rapporto fra componente pulsatile e continua. Ricostruito per riproduzione numerica: PP/MAP da 0,436, mentre PP/SBP darebbe 0,34.
A19: 15 | B19: Pompa | C19: Resistenze vascolari sistemiche (SVRI) | D19: 80 x (MAP - CVP) / CI / 1000 | E19: =80*(E7-'01 Input'!$B$26)/E16/1000 -> 2.713082 | F19: kU*m2 | G19: 2.7 | H19: =IF(G19=0,"",(E19-G19)/ABS(G19)) -> 0.0048452 | I19: 1.8 | J19: 2.8 | K19: Alto | L19: =IF(J19=I19,"",(E19-I19)/(J19-I19)) -> 0.91308204 | M19: =IF(E19>J19,"Fuori (alto)",IF(E19<I19,"Fuori (basso)",IF(AND(K19<>"Informativo",OR(AND(OR(K19="Alto",K19="Bilaterale"),L19>0.8),AND(OR(K19="Basso",K19="Bilaterale"),L19<0.2))),"Borderline","Normale"))) -> Borderline | N19: 2 | O19: =IF(N19=0,0,IF(AND(E19>J19,OR(K19="Alto",K19="Bilaterale")),IF((E19-J19)/(J19-I19)>0.1,3,2),IF(AND(E19<I19,OR(K19="Basso",K19="Bilaterale")),IF((I19-E19)/(J19-I19)>0.1,3,2),IF(M19="Borderline",1,0)))) -> 1 | P19: =N19*O19 -> 2 | Q19: Art.1 - Indici cardiologici | R19: A 0,1 dal limite superiore: le arterie oppongono resistenza vicina al massimo tollerato e il cuore risponde con la frequenza, non aumentando il volume di eiezione. CVP non pubblicata, assunta a 5 mmHg.
A20: 16 | B20: Antropom. | C20: Superficie corporea (BSA) | D20: input (formula non pubblicata) | E20: ='01 Input'!$B$18 -> 1.9 | F20: m2 | G20: 1.9 | H20: =IF(G20=0,"",(E20-G20)/ABS(G20)) -> 0 | I20: 1.5 | J20: 2.3 | K20: Informativo | L20: =IF(J20=I20,"",(E20-I20)/(J20-I20)) -> 0.5 | M20: =IF(E20>J20,"Fuori (alto)",IF(E20<I20,"Fuori (basso)",IF(AND(K20<>"Informativo",OR(AND(OR(K20="Alto",K20="Bilaterale"),L20>0.8),AND(OR(K20="Basso",K20="Bilaterale"),L20<0.2))),"Borderline","Normale"))) -> Normale | N20: 0 | O20: =IF(N20=0,0,IF(AND(E20>J20,OR(K20="Alto",K20="Bilaterale")),IF((E20-J20)/(J20-I20)>0.1,3,2),IF(AND(E20<I20,OR(K20="Basso",K20="Bilaterale")),IF((I20-E20)/(J20-I20)>0.1,3,2),IF(M20="Borderline",1,0)))) -> 0 | P20: =N20*O20 -> 0 | Q20: Art.1 - Indici cardiologici | R20: Inclusa come sedicesima riga: la fonte dichiara 16 indici cardiologici ma ne tabula 15. E il denominatore di CI, LCWI e SVRI. Peso 0.
A21: 17 | B21: Base | C21: Indice di massa corporea (BMI) | D21: peso / altezza^2 | E21: ='01 Input'!$B$11/('01 Input'!$B$12/100)^2 -> 24.441802 | F21: kg/m2 | G21: 24.09 | H21: =IF(G21=0,"",(E21-G21)/ABS(G21)) -> 0.014603657 | I21: 18.5 | J21: 24.9 | K21: Informativo | L21: =IF(J21=I21,"",(E21-I21)/(J21-I21)) -> 0.92840658 | M21: =IF(E21>J21,"Fuori (alto)",IF(E21<I21,"Fuori (basso)",IF(AND(K21<>"Informativo",OR(AND(OR(K21="Alto",K21="Bilaterale"),L21>0.8),AND(OR(K21="Basso",K21="Bilaterale"),L21<0.2))),"Borderline","Normale"))) -> Normale | N21: 0 | O21: =IF(N21=0,0,IF(AND(E21>J21,OR(K21="Alto",K21="Bilaterale")),IF((E21-J21)/(J21-I21)>0.1,3,2),IF(AND(E21<I21,OR(K21="Basso",K21="Bilaterale")),IF((I21-E21)/(J21-I21)>0.1,3,2),IF(M21="Borderline",1,0)))) -> 0 | P21: =N21*O21 -> 0 | Q21: Art.2 - Indici antropometrici | R21: ATTENZIONE: 74 kg su 174 cm danno 24,44, non i 24,09 pubblicati. Il referto usa internamente 24,09 (il VAI torna solo con quel valore). Peso 0 non perche sia irrilevante, ma perche e proprio l'indice che qui assolve un corpo in disordine. Vedi foglio 08.
A22: 18 | B22: Base | C22: Rapporto altezza / polso | D22: altezza / circonf. polso | E22: ='01 Input'!$B$12/'01 Input'!$B$16 -> 9.6666667 | F22: - | G22: 9.7 | H22: =IF(G22=0,"",(E22-G22)/ABS(G22)) -> -0.0034364261 | I22: 9.6 | J22: 10.4 | K22: Informativo | L22: =IF(J22=I22,"",(E22-I22)/(J22-I22)) -> 0.083333333 | M22: =IF(E22>J22,"Fuori (alto)",IF(E22<I22,"Fuori (basso)",IF(AND(K22<>"Informativo",OR(AND(OR(K22="Alto",K22="Bilaterale"),L22>0.8),AND(OR(K22="Basso",K22="Bilaterale"),L22<0.2))),"Borderline","Normale"))) -> Normale | N22: 0 | O22: =IF(N22=0,0,IF(AND(E22>J22,OR(K22="Alto",K22="Bilaterale")),IF((E22-J22)/(J22-I22)>0.1,3,2),IF(AND(E22<I22,OR(K22="Basso",K22="Bilaterale")),IF((I22-E22)/(J22-I22)>0.1,3,2),IF(M22="Borderline",1,0)))) -> 0 | P22: =N22*O22 -> 0 | Q22: Art.2 - Indici antropometrici | R22: Morfotipo normolineo. Al polso non c'e ne grasso apprezzabile ne ventre muscolare: e l'unica misura stabile per tutta la vita adulta, e quindi il riferimento fisso contro cui si giudicano gli indici che invece si muovono.
A23: 19 | B23: Base | C23: Peso ideale secondo Lorenz | D23: H - 100 - (H - 150)/4 | E23: ='01 Input'!$B$12-100-('01 Input'!$B$12-150)/4 -> 68 | F23: kg | G23: 68 | H23: =IF(G23=0,"",(E23-G23)/ABS(G23)) -> 0 | I23: 60 | J23: 80 | K23: Informativo | L23: =IF(J23=I23,"",(E23-I23)/(J23-I23)) -> 0.4 | M23: =IF(E23>J23,"Fuori (alto)",IF(E23<I23,"Fuori (basso)",IF(AND(K23<>"Informativo",OR(AND(OR(K23="Alto",K23="Bilaterale"),L23>0.8),AND(OR(K23="Basso",K23="Bilaterale"),L23<0.2))),"Borderline","Normale"))) -> Normale | N23: 0 | O23: =IF(N23=0,0,IF(AND(E23>J23,OR(K23="Alto",K23="Bilaterale")),IF((E23-J23)/(J23-I23)>0.1,3,2),IF(AND(E23<I23,OR(K23="Basso",K23="Bilaterale")),IF((I23-E23)/(J23-I23)>0.1,3,2),IF(M23="Borderline",1,0)))) -> 0 | P23: =N23*O23 -> 0 | Q23: Art.2 - Indici antropometrici | R23: Lavora sulla sola statura e ignora eta e corporatura. Estremo basso della forbice del peso desiderabile.
A24: 20 | B24: Base | C24: Peso ideale secondo Creff | D24: (H - 100 + eta/10) x 0,9 | E24: =('01 Input'!$B$12-100+'01 Input'!$B$7/10)*0.9 -> 71.1 | F24: kg | G24: 71.1 | H24: =IF(G24=0,"",(E24-G24)/ABS(G24)) -> 0 | I24: 60 | J24: 80 | K24: Informativo | L24: =IF(J24=I24,"",(E24-I24)/(J24-I24)) -> 0.555 | M24: =IF(E24>J24,"Fuori (alto)",IF(E24<I24,"Fuori (basso)",IF(AND(K24<>"Informativo",OR(AND(OR(K24="Alto",K24="Bilaterale"),L24>0.8),AND(OR(K24="Basso",K24="Bilaterale"),L24<0.2))),"Borderline","Normale"))) -> Normale | N24: 0 | O24: =IF(N24=0,0,IF(AND(E24>J24,OR(K24="Alto",K24="Bilaterale")),IF((E24-J24)/(J24-I24)>0.1,3,2),IF(AND(E24<I24,OR(K24="Basso",K24="Bilaterale")),IF((I24-E24)/(J24-I24)>0.1,3,2),IF(M24="Borderline",1,0)))) -> 0 | P24: =N24*O24 -> 0 | Q24: Art.2 - Indici antropometrici | R24: Corregge per eta e morfotipo. Con Lorenz definisce la forbice 68-71 kg: il soggetto a 74 kg sfora di meno di tre chili, margine che nessun clinico definirebbe allarmante. Il problema non e quanto pesa ma dove.
A25: 21 | B25: Forma | C25: Rapporto vita / altezza (WHtR) | D25: vita / altezza | E25: ='01 Input'!$B$13/'01 Input'!$B$12 -> 0.55747126 | F25: - | G25: 0.56 | H25: =IF(G25=0,"",(E25-G25)/ABS(G25)) -> -0.0045155993 | I25: 0.3 | J25: 0.52 | K25: Alto | L25: =IF(J25=I25,"",(E25-I25)/(J25-I25)) -> 1.1703239 | M25: =IF(E25>J25,"Fuori (alto)",IF(E25<I25,"Fuori (basso)",IF(AND(K25<>"Informativo",OR(AND(OR(K25="Alto",K25="Bilaterale"),L25>0.8),AND(OR(K25="Basso",K25="Bilaterale"),L25<0.2))),"Borderline","Normale"))) -> Fuori (alto) | N25: 3 | O25: =IF(N25=0,0,IF(AND(E25>J25,OR(K25="Alto",K25="Bilaterale")),IF((E25-J25)/(J25-I25)>0.1,3,2),IF(AND(E25<I25,OR(K25="Basso",K25="Bilaterale")),IF((I25-E25)/(J25-I25)>0.1,3,2),IF(M25="Borderline",1,0)))) -> 3 | P25: =N25*O25 -> 9 | Q25: Art.2 - Indici antropometrici | R25: La regola aurea vuole la vita sotto la meta dell'altezza. Meta-analisi di 31 studi: discrimina il rischio cardiometabolico meglio del BMI (PMID 22106927). E il primo indice da guardare, per velocita e robustezza.
A26: 22 | B26: Forma | C26: Rapporto vita / fianchi (WHR) | D26: vita / fianchi | E26: ='01 Input'!$B$13/'01 Input'!$B$14 -> 0.97 | F26: - | G26: 0.97 | H26: =IF(G26=0,"",(E26-G26)/ABS(G26)) -> 0 | I26: 0.7 | J26: 0.89 | K26: Alto | L26: =IF(J26=I26,"",(E26-I26)/(J26-I26)) -> 1.4210526 | M26: =IF(E26>J26,"Fuori (alto)",IF(E26<I26,"Fuori (basso)",IF(AND(K26<>"Informativo",OR(AND(OR(K26="Alto",K26="Bilaterale"),L26>0.8),AND(OR(K26="Basso",K26="Bilaterale"),L26<0.2))),"Borderline","Normale"))) -> Fuori (alto) | N26: 2 | O26: =IF(N26=0,0,IF(AND(E26>J26,OR(K26="Alto",K26="Bilaterale")),IF((E26-J26)/(J26-I26)>0.1,3,2),IF(AND(E26<I26,OR(K26="Basso",K26="Bilaterale")),IF((I26-E26)/(J26-I26)>0.1,3,2),IF(M26="Borderline",1,0)))) -> 3 | P26: =N26*O26 -> 6 | Q26: Art.2 - Indici antropometrici | R26: Forma a mela: distribuzione addominale del grasso, la peggiore dal punto di vista metabolico.
A27: 23 | B27: Forma | C27: Conicity Index | D27: (vita/100) / (0,109 x RADQ(peso/altezza_m)) | E27: =('01 Input'!$B$13/100)/(0.109*SQRT('01 Input'!$B$11/('01 Input'!$B$12/100))) -> 1.3645957 | F27: - | G27: 1.36 | H27: =IF(G27=0,"",(E27-G27)/ABS(G27)) -> 0.0033791962 | I27: 1 | J27: 1.25 | K27: Alto | L27: =IF(J27=I27,"",(E27-I27)/(J27-I27)) -> 1.4583828 | M27: =IF(E27>J27,"Fuori (alto)",IF(E27<I27,"Fuori (basso)",IF(AND(K27<>"Informativo",OR(AND(OR(K27="Alto",K27="Bilaterale"),L27>0.8),AND(OR(K27="Basso",K27="Bilaterale"),L27<0.2))),"Borderline","Normale"))) -> Fuori (alto) | N27: 2 | O27: =IF(N27=0,0,IF(AND(E27>J27,OR(K27="Alto",K27="Bilaterale")),IF((E27-J27)/(J27-I27)>0.1,3,2),IF(AND(E27<I27,OR(K27="Basso",K27="Bilaterale")),IF((I27-E27)/(J27-I27)>0.1,3,2),IF(M27="Borderline",1,0)))) -> 3 | P27: =N27*O27 -> 6 | Q27: Art.2 - Indici antropometrici | R27: Descrive quanto il tronco si allontana dal cilindro per avvicinarsi al doppio cono. Normalizza la vita per peso e statura, quindi l'addome sporge al netto della corporatura.
A28: 24 | B28: Adiposita | C28: Percentuale di grasso corporeo | D28: Deurenberg: 1,2xBMI + 0,23xeta - 10,8xsesso - 5,4 | E28: =1.2*E21+0.23*'01 Input'!$B$7-10.8*IF('01 Input'!$B$8="M",1,0)-5.4 -> 24.630163 | F28: % | G28: 23 | H28: =IF(G28=0,"",(E28-G28)/ABS(G28)) -> 0.070876631 | I28: 8 | J28: 25 | K28: Alto | L28: =IF(J28=I28,"",(E28-I28)/(J28-I28)) -> 0.97824485 | M28: =IF(E28>J28,"Fuori (alto)",IF(E28<I28,"Fuori (basso)",IF(AND(K28<>"Informativo",OR(AND(OR(K28="Alto",K28="Bilaterale"),L28>0.8),AND(OR(K28="Basso",K28="Bilaterale"),L28<0.2))),"Borderline","Normale"))) -> Borderline | N28: 1 | O28: =IF(N28=0,0,IF(AND(E28>J28,OR(K28="Alto",K28="Bilaterale")),IF((E28-J28)/(J28-I28)>0.1,3,2),IF(AND(E28<I28,OR(K28="Basso",K28="Bilaterale")),IF((I28-E28)/(J28-I28)>0.1,3,2),IF(M28="Borderline",1,0)))) -> 1 | P28: =N28*O28 -> 1 | Q28: Art.2 - Indici antropometrici | R28: Formula non dichiarata dalla fonte: Deurenberg e la piu probabile ma restituisce 24,6 contro i 23 pubblicati. Stima derivata dal BMI, quindi eredita il difetto del BMI di non distinguere i tessuti.
A29: 25 | B29: Adiposita | C29: Body Adiposity Index (BAI) | D29: fianchi / altezza_m^1,5 - 18 | E29: ='01 Input'!$B$14/(('01 Input'!$B$12/100)^1.5)-18 -> 25.568853 | F29: % | G29: 25 | H29: =IF(G29=0,"",(E29-G29)/ABS(G29)) -> 0.022754123 | I29: 8 | J29: 23 | K29: Alto | L29: =IF(J29=I29,"",(E29-I29)/(J29-I29)) -> 1.1712569 | M29: =IF(E29>J29,"Fuori (alto)",IF(E29<I29,"Fuori (basso)",IF(AND(K29<>"Informativo",OR(AND(OR(K29="Alto",K29="Bilaterale"),L29>0.8),AND(OR(K29="Basso",K29="Bilaterale"),L29<0.2))),"Borderline","Normale"))) -> Fuori (alto) | N29: 2 | O29: =IF(N29=0,0,IF(AND(E29>J29,OR(K29="Alto",K29="Bilaterale")),IF((E29-J29)/(J29-I29)>0.1,3,2),IF(AND(E29<I29,OR(K29="Basso",K29="Bilaterale")),IF((I29-E29)/(J29-I29)>0.1,3,2),IF(M29="Borderline",1,0)))) -> 3 | P29: =N29*O29 -> 6 | Q29: Art.2 - Indici antropometrici | R29: Ricava l'adiposita da fianchi e altezza senza mai usare il peso. Quando due indici di adiposita divergono sulla stessa persona vince quello che non usa il peso, perche e il peso a mascherare la ricomposizione corporea.
A30: 26 | B30: Adiposita | C30: Body Roundness Index (BRI) | D30: 364,2 - 365,5 x RADQ(1 - ((vita/2pi)/(0,5xH))^2) | E30: =364.2-365.5*SQRT(1-((('01 Input'!$B$13/100)/(2*PI()))/(0.5*('01 Input'!$B$12/100)))^2) -> 4.5004604 | F30: - | G30: 4.5 | H30: =IF(G30=0,"",(E30-G30)/ABS(G30)) -> 0.00010232089 | I30: 1 | J30: 4.71 | K30: Alto | L30: =IF(J30=I30,"",(E30-I30)/(J30-I30)) -> 0.94352034 | M30: =IF(E30>J30,"Fuori (alto)",IF(E30<I30,"Fuori (basso)",IF(AND(K30<>"Informativo",OR(AND(OR(K30="Alto",K30="Bilaterale"),L30>0.8),AND(OR(K30="Basso",K30="Bilaterale"),L30<0.2))),"Borderline","Normale"))) -> Borderline | N30: 1 | O30: =IF(N30=0,0,IF(AND(E30>J30,OR(K30="Alto",K30="Bilaterale")),IF((E30-J30)/(J30-I30)>0.1,3,2),IF(AND(E30<I30,OR(K30="Basso",K30="Bilaterale")),IF((I30-E30)/(J30-I30)>0.1,3,2),IF(M30="Borderline",1,0)))) -> 1 | P30: =N30*O30 -> 1 | Q30: Art.2 - Indici antropometrici | R30: Uno dei due indici assolti del gruppo, e va registrato con onestà. Dentro il riferimento, ma nell'ultimo 10% dell'intervallo.
A31: 27 | B31: Adiposita | C31: Abdominal Volume Index (AVI) | D31: (2 x vita^2 + 0,7 x (vita-fianchi)^2) / 1000 | E31: =(2*'01 Input'!$B$13^2+0.7*('01 Input'!$B$13-'01 Input'!$B$14)^2)/1000 -> 18.8243 | F31: - | G31: 11.89 | H31: =IF(G31=0,"",(E31-G31)/ABS(G31)) -> 0.58320437 | I31: 0 | J31: 24.5 | K31: Alto | L31: =IF(J31=I31,"",(E31-I31)/(J31-I31)) -> 0.76833878 | M31: =IF(E31>J31,"Fuori (alto)",IF(E31<I31,"Fuori (basso)",IF(AND(K31<>"Informativo",OR(AND(OR(K31="Alto",K31="Bilaterale"),L31>0.8),AND(OR(K31="Basso",K31="Bilaterale"),L31<0.2))),"Borderline","Normale"))) -> Normale | N31: 1 | O31: =IF(N31=0,0,IF(AND(E31>J31,OR(K31="Alto",K31="Bilaterale")),IF((E31-J31)/(J31-I31)>0.1,3,2),IF(AND(E31<I31,OR(K31="Basso",K31="Bilaterale")),IF((I31-E31)/(J31-I31)>0.1,3,2),IF(M31="Borderline",1,0)))) -> 0 | P31: =N31*O31 -> 0 | Q31: Art.2 - Indici antropometrici | R31: NON RIPRODUCIBILE: la formula standard restituisce 18,82 contro gli 11,89 pubblicati. L'esito resta 'dentro il riferimento' con entrambi i valori, quindi la conclusione non cambia, ma il numero non torna. Vedi foglio 08.
A32: 28 | B32: Ibridi | C32: Lipid Accumulation Product (LAP) | D32: (vita - 65) x trigliceridi in mmol/L | E32: =('01 Input'!$B$13-65)*('01 Input'!$B$30/88.57) -> 53.47183 | F32: - | G32: 53.5 | H32: =IF(G32=0,"",(E32-G32)/ABS(G32)) -> -0.00052653849 | I32: 0 | J32: 26.7 | K32: Alto | L32: =IF(J32=I32,"",(E32-I32)/(J32-I32)) -> 2.0026903 | M32: =IF(E32>J32,"Fuori (alto)",IF(E32<I32,"Fuori (basso)",IF(AND(K32<>"Informativo",OR(AND(OR(K32="Alto",K32="Bilaterale"),L32>0.8),AND(OR(K32="Basso",K32="Bilaterale"),L32<0.2))),"Borderline","Normale"))) -> Fuori (alto) | N32: 3 | O32: =IF(N32=0,0,IF(AND(E32>J32,OR(K32="Alto",K32="Bilaterale")),IF((E32-J32)/(J32-I32)>0.1,3,2),IF(AND(E32<I32,OR(K32="Basso",K32="Bilaterale")),IF((I32-E32)/(J32-I32)>0.1,3,2),IF(M32="Borderline",1,0)))) -> 3 | P32: =N32*O32 -> 9 | Q32: Art.2 - Indici antropometrici | R32: Il doppio esatto del cut-off. Riconosce il rischio cardiovascolare meglio del BMI (PMID 16150143). Nasce dall'incrocio fra una vita di 97 cm e trigliceridi che presi da soli nessun laboratorio segnalerebbe.
A33: 29 | B33: Ibridi | C33: Cardiometabolic Index (CMI) | D33: (vita/altezza) x (TG/HDL) in mmol/L | E33: =('01 Input'!$B$13/'01 Input'!$B$12)*(('01 Input'!$B$30/88.57)/('01 Input'!$B$29/38.67)) -> 0.87859327 | F33: - | G33: 0.88 | H33: =IF(G33=0,"",(E33-G33)/ABS(G33)) -> -0.0015985573 | I33: 0 | J33: 0.39 | K33: Alto | L33: =IF(J33=I33,"",(E33-I33)/(J33-I33)) -> 2.2528033 | M33: =IF(E33>J33,"Fuori (alto)",IF(E33<I33,"Fuori (basso)",IF(AND(K33<>"Informativo",OR(AND(OR(K33="Alto",K33="Bilaterale"),L33>0.8),AND(OR(K33="Basso",K33="Bilaterale"),L33<0.2))),"Borderline","Normale"))) -> Fuori (alto) | N33: 2 | O33: =IF(N33=0,0,IF(AND(E33>J33,OR(K33="Alto",K33="Bilaterale")),IF((E33-J33)/(J33-I33)>0.1,3,2),IF(AND(E33<I33,OR(K33="Basso",K33="Bilaterale")),IF((I33-E33)/(J33-I33)>0.1,3,2),IF(M33="Borderline",1,0)))) -> 3 | P33: =N33*O33 -> 6 | Q33: Art.2 - Indici antropometrici | R33: Piu del doppio del cut-off. Buon discriminatore di diabete e disglicemia (PMID 25199852). Va calcolato in mmol/L: usando i mg/dL verrebbe 2,01, un numero che non ha piu alcun rapporto con la soglia.
A34: 30 | B34: Ibridi | C34: Visceral Adiposity Index (VAI) | D34: (vita/(39,68+1,88xBMI)) x (TG/1,03) x (1,31/HDL), mmol/L | E34: =('01 Input'!$B$13/(39.68+1.88*E21))*(('01 Input'!$B$30/88.57)/1.03)*(1.31/('01 Input'!$B$29/38.67)) -> 2.2706085 | F34: - | G34: 2.29 | H34: =IF(G34=0,"",(E34-G34)/ABS(G34)) -> -0.0084678898 | I34: 0 | J34: 1.92 | K34: Alto | L34: =IF(J34=I34,"",(E34-I34)/(J34-I34)) -> 1.1826086 | M34: =IF(E34>J34,"Fuori (alto)",IF(E34<I34,"Fuori (basso)",IF(AND(K34<>"Informativo",OR(AND(OR(K34="Alto",K34="Bilaterale"),L34>0.8),AND(OR(K34="Basso",K34="Bilaterale"),L34<0.2))),"Borderline","Normale"))) -> Fuori (alto) | N34: 3 | O34: =IF(N34=0,0,IF(AND(E34>J34,OR(K34="Alto",K34="Bilaterale")),IF((E34-J34)/(J34-I34)>0.1,3,2),IF(AND(E34<I34,OR(K34="Basso",K34="Bilaterale")),IF((I34-E34)/(J34-I34)>0.1,3,2),IF(M34="Borderline",1,0)))) -> 3 | P34: =N34*O34 -> 9 | Q34: Art.2 - Indici antropometrici | R34: Marcatore della FUNZIONE del tessuto adiposo viscerale, non della sua quantita (PMID 20067971). Il referto commenta: disfunzione moderata del tessuto adiposo, resistenza insulinica presente. E l'indice che rivela il BMI usato internamente dal referto.
A35: 31 | B35: Mortalita | C35: A Body Shape Index (ABSI) - z-score | D35: z da tabelle NHANES per eta e sesso | E35: ='01 Input'!$B$55 -> 1.52 | F35: z | G35: 1.52 | H35: =IF(G35=0,"",(E35-G35)/ABS(G35)) -> 0 | I35: -0.272 | J35: 0.228 | K35: Alto | L35: =IF(J35=I35,"",(E35-I35)/(J35-I35)) -> 3.584 | M35: =IF(E35>J35,"Fuori (alto)",IF(E35<I35,"Fuori (basso)",IF(AND(K35<>"Informativo",OR(AND(OR(K35="Alto",K35="Bilaterale"),L35>0.8),AND(OR(K35="Basso",K35="Bilaterale"),L35<0.2))),"Borderline","Normale"))) -> Fuori (alto) | N35: 3 | O35: =IF(N35=0,0,IF(AND(E35>J35,OR(K35="Alto",K35="Bilaterale")),IF((E35-J35)/(J35-I35)>0.1,3,2),IF(AND(E35<I35,OR(K35="Basso",K35="Bilaterale")),IF((I35-E35)/(J35-I35)>0.1,3,2),IF(M35="Borderline",1,0)))) -> 3 | P35: =N35*O35 -> 9 | Q35: Art.2 - Indici antropometrici | R35: L'unico indice il cui commento non ammette diplomazia: rischio di mortalita molto alto. Costruito su 14.105 adulti NHANES per isolare la forma corporea depurata da peso e BMI, con aumento quasi esponenziale della mortalita (PMID 22815707). E l'indice che un normopeso non si aspetta mai di trovare alterato. Il valore grezzo di ABSI e ricalcolabile (0,0873), lo z-score no: le tabelle di riferimento non sono pubblicate.
A36: 32 | B36: Muscolo | C36: Circonferenza polpaccio corretta per BMI | D36: CC - correzione categoriale EWGSOP2 | E36: ='01 Input'!$B$15-IF(E21<18.5,-4,IF(E21<25,0,IF(E21<30,3,7))) -> 34 | F36: cm | G36: 33.5 | H36: =IF(G36=0,"",(E36-G36)/ABS(G36)) -> 0.014925373 | I36: 34 | J36: 45 | K36: Basso | L36: =IF(J36=I36,"",(E36-I36)/(J36-I36)) -> 0 | M36: =IF(E36>J36,"Fuori (alto)",IF(E36<I36,"Fuori (basso)",IF(AND(K36<>"Informativo",OR(AND(OR(K36="Alto",K36="Bilaterale"),L36>0.8),AND(OR(K36="Basso",K36="Bilaterale"),L36<0.2))),"Borderline","Normale"))) -> Borderline | N36: 3 | O36: =IF(N36=0,0,IF(AND(E36>J36,OR(K36="Alto",K36="Bilaterale")),IF((E36-J36)/(J36-I36)>0.1,3,2),IF(AND(E36<I36,OR(K36="Basso",K36="Bilaterale")),IF((I36-E36)/(J36-I36)>0.1,3,2),IF(M36="Borderline",1,0)))) -> 1 | P36: =N36*O36 -> 3 | Q36: Art.2 - Indici antropometrici | R36: Surrogato validato della massa muscolare appendicolare (PMID 30312372). La correzione applicata dal referto non e pubblicata: con quella categoriale EWGSOP2 il BMI del soggetto non comporta alcuna correzione e il valore resterebbe 34,0 cm, cioe ESATTAMENTE sulla soglia invece che sotto. La diagnosi di sarcopenia moderata dipende interamente da quei 5 millimetri non documentati.
A37: 33 | B37: Ferro circolante | C37: Sideremia | D37: misurata | E37: ='01 Input'!$B$33 -> 13.6 | F37: uM | G37: 13.6 | H37: =IF(G37=0,"",(E37-G37)/ABS(G37)) -> 0 | I37: 13 | J37: 27 | K37: Basso | L37: =IF(J37=I37,"",(E37-I37)/(J37-I37)) -> 0.042857143 | M37: =IF(E37>J37,"Fuori (alto)",IF(E37<I37,"Fuori (basso)",IF(AND(K37<>"Informativo",OR(AND(OR(K37="Alto",K37="Bilaterale"),L37>0.8),AND(OR(K37="Basso",K37="Bilaterale"),L37<0.2))),"Borderline","Normale"))) -> Borderline | N37: 2 | O37: =IF(N37=0,0,IF(AND(E37>J37,OR(K37="Alto",K37="Bilaterale")),IF((E37-J37)/(J37-I37)>0.1,3,2),IF(AND(E37<I37,OR(K37="Basso",K37="Bilaterale")),IF((I37-E37)/(J37-I37)>0.1,3,2),IF(M37="Borderline",1,0)))) -> 1 | P37: =N37*O37 -> 2 | Q37: Art.3 - Profilo marziale | R37: Dentro l'intervallo per sei decimi di micromole: e il valore piu basso possibile senza essere segnalato. Ha un ritmo circadiano marcato, quindi un prelievo pomeridiano abbasserebbe la saturazione di diversi punti senza che le riserve siano cambiate.
A38: 34 | B38: Ferro circolante | C38: Sideremia aggiustata per infiammazione | D38: sideremia x fattore BRINDA | E38: ='01 Input'!$B$33*'01 Input'!$B$36 -> 17.10064 | F38: uM | G38: 17.1 | H38: =IF(G38=0,"",(E38-G38)/ABS(G38)) -> 3.7426901e-05 | I38: 15 | J38: 23 | K38: Basso | L38: =IF(J38=I38,"",(E38-I38)/(J38-I38)) -> 0.26258 | M38: =IF(E38>J38,"Fuori (alto)",IF(E38<I38,"Fuori (basso)",IF(AND(K38<>"Informativo",OR(AND(OR(K38="Alto",K38="Bilaterale"),L38>0.8),AND(OR(K38="Basso",K38="Bilaterale"),L38<0.2))),"Borderline","Normale"))) -> Normale | N38: 1 | O38: =IF(N38=0,0,IF(AND(E38>J38,OR(K38="Alto",K38="Bilaterale")),IF((E38-J38)/(J38-I38)>0.1,3,2),IF(AND(E38<I38,OR(K38="Basso",K38="Bilaterale")),IF((I38-E38)/(J38-I38)>0.1,3,2),IF(M38="Borderline",1,0)))) -> 0 | P38: =N38*O38 -> 0 | Q38: Art.3 - Profilo marziale | R38: La correzione per l'infiammazione alza il ferro circolante e abbassa la ferritina, cioe spinge le due grandezze in direzioni opposte. Il fattore non e pubblicato: e stato dedotto dal rapporto fra valore aggiustato e valore grezzo.
A39: 35 | B39: Trasporto | C39: Transferrina | D39: misurata | E39: ='01 Input'!$B$34 -> 39.2 | F39: uM | G39: 39.2 | H39: =IF(G39=0,"",(E39-G39)/ABS(G39)) -> 0 | I39: 25.1 | J39: 50.3 | K39: Alto | L39: =IF(J39=I39,"",(E39-I39)/(J39-I39)) -> 0.55952381 | M39: =IF(E39>J39,"Fuori (alto)",IF(E39<I39,"Fuori (basso)",IF(AND(K39<>"Informativo",OR(AND(OR(K39="Alto",K39="Bilaterale"),L39>0.8),AND(OR(K39="Basso",K39="Bilaterale"),L39<0.2))),"Borderline","Normale"))) -> Normale | N39: 1 | O39: =IF(N39=0,0,IF(AND(E39>J39,OR(K39="Alto",K39="Bilaterale")),IF((E39-J39)/(J39-I39)>0.1,3,2),IF(AND(E39<I39,OR(K39="Basso",K39="Bilaterale")),IF((I39-E39)/(J39-I39)>0.1,3,2),IF(M39="Borderline",1,0)))) -> 0 | P39: =N39*O39 -> 0 | Q39: Art.3 - Profilo marziale | R39: Il camion che trasporta il ferro. Il fegato ne produce di piu proprio quando il ferro scarseggia, quindi un valore alto e un segnale di carenza, non di abbondanza.
A40: 36 | B40: Trasporto | C40: TIBC (capacita totale legante) | D40: 2 x transferrina | E40: =2*E39 -> 78.4 | F40: uM | G40: 78.4 | H40: =IF(G40=0,"",(E40-G40)/ABS(G40)) -> 0 | I40: 45 | J40: 76 | K40: Alto | L40: =IF(J40=I40,"",(E40-I40)/(J40-I40)) -> 1.0774194 | M40: =IF(E40>J40,"Fuori (alto)",IF(E40<I40,"Fuori (basso)",IF(AND(K40<>"Informativo",OR(AND(OR(K40="Alto",K40="Bilaterale"),L40>0.8),AND(OR(K40="Basso",K40="Bilaterale"),L40<0.2))),"Borderline","Normale"))) -> Fuori (alto) | N40: 1 | O40: =IF(N40=0,0,IF(AND(E40>J40,OR(K40="Alto",K40="Bilaterale")),IF((E40-J40)/(J40-I40)>0.1,3,2),IF(AND(E40<I40,OR(K40="Basso",K40="Bilaterale")),IF((I40-E40)/(J40-I40)>0.1,3,2),IF(M40="Borderline",1,0)))) -> 2 | P40: =N40*O40 -> 2 | Q40: Art.3 - Profilo marziale | R40: Ogni molecola di transferrina lega due atomi di ferro: da qui il fattore 2, che riproduce esattamente il valore pubblicato. Oltre la finestra ottimale significa che circolano molti posti liberi sui camion.
A41: 37 | B41: Trasporto | C41: UIBC (capacita legante insatura) | D41: TIBC - sideremia | E41: =E40-E37 -> 64.8 | F41: uM | G41: 64.8 | H41: =IF(G41=0,"",(E41-G41)/ABS(G41)) -> 0 | I41: 22 | J41: 61 | K41: Alto | L41: =IF(J41=I41,"",(E41-I41)/(J41-I41)) -> 1.0974359 | M41: =IF(E41>J41,"Fuori (alto)",IF(E41<I41,"Fuori (basso)",IF(AND(K41<>"Informativo",OR(AND(OR(K41="Alto",K41="Bilaterale"),L41>0.8),AND(OR(K41="Basso",K41="Bilaterale"),L41<0.2))),"Borderline","Normale"))) -> Fuori (alto) | N41: 1 | O41: =IF(N41=0,0,IF(AND(E41>J41,OR(K41="Alto",K41="Bilaterale")),IF((E41-J41)/(J41-I41)>0.1,3,2),IF(AND(E41<I41,OR(K41="Basso",K41="Bilaterale")),IF((I41-E41)/(J41-I41)>0.1,3,2),IF(M41="Borderline",1,0)))) -> 2 | P41: =N41*O41 -> 2 | Q41: Art.3 - Profilo marziale | R41: I posti liberi effettivi. Conferma dall'altro lato quello che dice la saturazione: la capacita di trasporto c'e, il carico no.
A42: 38 | B42: Disponibilita | C42: Saturazione della transferrina | D42: sideremia / TIBC x 100 | E42: =E37/E40*100 -> 17.346939 | F42: % | G42: 17.3 | H42: =IF(G42=0,"",(E42-G42)/ABS(G42)) -> 0.002713224 | I42: 20 | J42: 48 | K42: Basso | L42: =IF(J42=I42,"",(E42-I42)/(J42-I42)) -> -0.094752187 | M42: =IF(E42>J42,"Fuori (alto)",IF(E42<I42,"Fuori (basso)",IF(AND(K42<>"Informativo",OR(AND(OR(K42="Alto",K42="Bilaterale"),L42>0.8),AND(OR(K42="Basso",K42="Bilaterale"),L42<0.2))),"Borderline","Normale"))) -> Fuori (basso) | N42: 3 | O42: =IF(N42=0,0,IF(AND(E42>J42,OR(K42="Alto",K42="Bilaterale")),IF((E42-J42)/(J42-I42)>0.1,3,2),IF(AND(E42<I42,OR(K42="Basso",K42="Bilaterale")),IF((I42-E42)/(J42-I42)>0.1,3,2),IF(M42="Borderline",1,0)))) -> 2 | P42: =N42*O42 -> 6 | Q42: Art.3 - Profilo marziale | R42: L'UNICO valore dell'intero pannello sotto il riferimento anche senza aggiustamenti, ed e considerato il marcatore piu informativo dello stato marziale reale perche mette insieme ferro circolante e proteina di trasporto (PMID 27346617, PMID 36380788). I camion viaggiano pieni per un sesto quando dovrebbero stare almeno a un quinto.
A43: 39 | B43: Disponibilita | C43: Saturazione aggiustata | D43: sideremia aggiustata / TIBC x 100 | E43: =E38/E40*100 -> 21.812041 | F43: % | G43: 21.8 | H43: =IF(G43=0,"",(E43-G43)/ABS(G43)) -> 0.00055233102 | I43: 24 | J43: 35 | K43: Basso | L43: =IF(J43=I43,"",(E43-I43)/(J43-I43)) -> -0.19890538 | M43: =IF(E43>J43,"Fuori (alto)",IF(E43<I43,"Fuori (basso)",IF(AND(K43<>"Informativo",OR(AND(OR(K43="Alto",K43="Bilaterale"),L43>0.8),AND(OR(K43="Basso",K43="Bilaterale"),L43<0.2))),"Borderline","Normale"))) -> Fuori (basso) | N43: 2 | O43: =IF(N43=0,0,IF(AND(E43>J43,OR(K43="Alto",K43="Bilaterale")),IF((E43-J43)/(J43-I43)>0.1,3,2),IF(AND(E43<I43,OR(K43="Basso",K43="Bilaterale")),IF((I43-E43)/(J43-I43)>0.1,3,2),IF(M43="Borderline",1,0)))) -> 3 | P43: =N43*O43 -> 6 | Q43: Art.3 - Profilo marziale | R43: Anche dopo la correzione che alza il ferro circolante, la saturazione resta sotto la finestra ottimale. La carenza funzionale non e un artefatto dell'infiammazione.
A44: 40 | B44: Depositi | C44: Ferritina | D44: misurata | E44: ='01 Input'!$B$35 -> 160.9 | F44: pM | G44: 160.9 | H44: =IF(G44=0,"",(E44-G44)/ABS(G44)) -> 0 | I44: 54 | J44: 854 | K44: Informativo | L44: =IF(J44=I44,"",(E44-I44)/(J44-I44)) -> 0.133625 | M44: =IF(E44>J44,"Fuori (alto)",IF(E44<I44,"Fuori (basso)",IF(AND(K44<>"Informativo",OR(AND(OR(K44="Alto",K44="Bilaterale"),L44>0.8),AND(OR(K44="Basso",K44="Bilaterale"),L44<0.2))),"Borderline","Normale"))) -> Normale | N44: 0 | O44: =IF(N44=0,0,IF(AND(E44>J44,OR(K44="Alto",K44="Bilaterale")),IF((E44-J44)/(J44-I44)>0.1,3,2),IF(AND(E44<I44,OR(K44="Basso",K44="Bilaterale")),IF((I44-E44)/(J44-I44)>0.1,3,2),IF(M44="Borderline",1,0)))) -> 0 | P44: =N44*O44 -> 0 | Q44: Art.3 - Profilo marziale | R44: Comoda nel mezzo di un intervallo larghissimo, ed e la riga su cui quasi tutti si fermano. Peso 0 come il BMI dell'articolo 2, e per la stessa ragione: e una proteina di fase acuta, quindi in un fumatore da trent'anni con flogosi cronica misura l'infiammazione piu delle riserve. Correggendo per infiammazione con il metodo BRINDA la prevalenza di carenza sale dal 46,3% al 61,5% (PMID 35623855).
A45: 41 | B45: Depositi | C45: Ferritina aggiustata per infiammazione | D45: ferritina x fattore BRINDA | E45: ='01 Input'!$B$35*'01 Input'!$B$37 -> 120.70718 | F45: pM | G45: 120.7 | H45: =IF(G45=0,"",(E45-G45)/ABS(G45)) -> 5.948633e-05 | I45: 283.1 | J45: 854 | K45: Basso | L45: =IF(J45=I45,"",(E45-I45)/(J45-I45)) -> -0.28445055 | M45: =IF(E45>J45,"Fuori (alto)",IF(E45<I45,"Fuori (basso)",IF(AND(K45<>"Informativo",OR(AND(OR(K45="Alto",K45="Bilaterale"),L45>0.8),AND(OR(K45="Basso",K45="Bilaterale"),L45<0.2))),"Borderline","Normale"))) -> Fuori (basso) | N45: 3 | O45: =IF(N45=0,0,IF(AND(E45>J45,OR(K45="Alto",K45="Bilaterale")),IF((E45-J45)/(J45-I45)>0.1,3,2),IF(AND(E45<I45,OR(K45="Basso",K45="Bilaterale")),IF((I45-E45)/(J45-I45)>0.1,3,2),IF(M45="Borderline",1,0)))) -> 3 | P45: =N45*O45 -> 9 | Q45: Art.3 - Profilo marziale | R45: Meno della meta del valore ottimale. E la riga che nessuno guarda e che ribalta la lettura della riga precedente: il commento del laboratorio sulla stessa fascia dice depositi midollari in esaurimento.
A46: 42 | B46: Depositi | C46: Depositi di ferro | D46: ferritina x 4,5 | E46: ='01 Input'!$B$35*4.5 -> 724.05 | F46: nM | G46: 724 | H46: =IF(G46=0,"",(E46-G46)/ABS(G46)) -> 6.9060773e-05 | I46: 301.5 | J46: 706.5 | K46: Bilaterale | L46: =IF(J46=I46,"",(E46-I46)/(J46-I46)) -> 1.0433333 | M46: =IF(E46>J46,"Fuori (alto)",IF(E46<I46,"Fuori (basso)",IF(AND(K46<>"Informativo",OR(AND(OR(K46="Alto",K46="Bilaterale"),L46>0.8),AND(OR(K46="Basso",K46="Bilaterale"),L46<0.2))),"Borderline","Normale"))) -> Fuori (alto) | N46: 1 | O46: =IF(N46=0,0,IF(AND(E46>J46,OR(K46="Alto",K46="Bilaterale")),IF((E46-J46)/(J46-I46)>0.1,3,2),IF(AND(E46<I46,OR(K46="Basso",K46="Bilaterale")),IF((I46-E46)/(J46-I46)>0.1,3,2),IF(M46="Borderline",1,0)))) -> 2 | P46: =N46*O46 -> 2 | Q46: Art.3 - Profilo marziale | R46: Il fattore 4,5 deriva dai circa 4500 atomi di ferro che ogni molecola di ferritina puo contenere, con la conversione da pM a nM. Sopra la finestra ottimale: ferro presente ma sequestrato, non ferro in eccesso. Calcolandolo sulla ferritina AGGIUSTATA darebbe 543 nM, cioe dentro la finestra: la contraddizione fra le due righe e il cuore del referto non discriminante.
A47: 43 | B47: Indici derivati | C47: Transferrina / log(ferritina) | D47: transferrina g/L / log10(ferritina ug/L) | E47: =('01 Input'!$B$34*0.07957)/LOG10('01 Input'!$B$35*0.45) -> 1.6771678 | F47: - | G47: 1.63 | H47: =IF(G47=0,"",(E47-G47)/ABS(G47)) -> 0.02893732 | I47: 0 | J47: 1.7 | K47: Alto | L47: =IF(J47=I47,"",(E47-I47)/(J47-I47)) -> 0.98656931 | M47: =IF(E47>J47,"Fuori (alto)",IF(E47<I47,"Fuori (basso)",IF(AND(K47<>"Informativo",OR(AND(OR(K47="Alto",K47="Bilaterale"),L47>0.8),AND(OR(K47="Basso",K47="Bilaterale"),L47<0.2))),"Borderline","Normale"))) -> Borderline | N47: 2 | O47: =IF(N47=0,0,IF(AND(E47>J47,OR(K47="Alto",K47="Bilaterale")),IF((E47-J47)/(J47-I47)>0.1,3,2),IF(AND(E47<I47,OR(K47="Basso",K47="Bilaterale")),IF((I47-E47)/(J47-I47)>0.1,3,2),IF(M47="Borderline",1,0)))) -> 1 | P47: =N47*O47 -> 2 | Q47: Art.3 - Profilo marziale | R47: Indice combinato per la carenza marziale in presenza di infiammazione. Il valore dipende dai pesi molecolari usati per la conversione in unita convenzionali, che la fonte non dichiara: al variare di quelli plausibili il risultato oscilla fra 1,59 e 1,70, e l'1,63 pubblicato cade dentro questa banda. Comunque a ridosso del cut-off.
A48: 44 | B48: Classici | C48: Proteina C reattiva (PCR) | D48: misurata | E48: ='01 Input'!$B$40 -> 0.3 | F48: mg/dL | G48: 0.3 | H48: =IF(G48=0,"",(E48-G48)/ABS(G48)) -> 0 | I48: 0 | J48: 0.5 | K48: Informativo | L48: =IF(J48=I48,"",(E48-I48)/(J48-I48)) -> 0.6 | M48: =IF(E48>J48,"Fuori (alto)",IF(E48<I48,"Fuori (basso)",IF(AND(K48<>"Informativo",OR(AND(OR(K48="Alto",K48="Bilaterale"),L48>0.8),AND(OR(K48="Basso",K48="Bilaterale"),L48<0.2))),"Borderline","Normale"))) -> Normale | N48: 0 | O48: =IF(N48=0,0,IF(AND(E48>J48,OR(K48="Alto",K48="Bilaterale")),IF((E48-J48)/(J48-I48)>0.1,3,2),IF(AND(E48<I48,OR(K48="Basso",K48="Bilaterale")),IF((I48-E48)/(J48-I48)>0.1,3,2),IF(M48="Borderline",1,0)))) -> 0 | P48: =N48*O48 -> 0 | Q48: Art.4 - Indici infiammatori | R48: Peso 0 come il BMI e come la ferritina, e per la stessa ragione: e un esame giusto per la domanda sbagliata. Sale molto e in fretta nell'infiammazione acuta, quindi non intercetta l'infiammazione cronica di basso grado, che non e un incendio ma un fornello lasciato acceso per vent'anni.
A49: 45 | B49: Classici | C49: VES a 1 ora | D49: misurata | E49: ='01 Input'!$B$41 -> 14 | F49: mm | G49: 14 | H49: =IF(G49=0,"",(E49-G49)/ABS(G49)) -> 0 | I49: 1 | J49: 25 | K49: Informativo | L49: =IF(J49=I49,"",(E49-I49)/(J49-I49)) -> 0.54166667 | M49: =IF(E49>J49,"Fuori (alto)",IF(E49<I49,"Fuori (basso)",IF(AND(K49<>"Informativo",OR(AND(OR(K49="Alto",K49="Bilaterale"),L49>0.8),AND(OR(K49="Basso",K49="Bilaterale"),L49<0.2))),"Borderline","Normale"))) -> Normale | N49: 0 | O49: =IF(N49=0,0,IF(AND(E49>J49,OR(K49="Alto",K49="Bilaterale")),IF((E49-J49)/(J49-I49)>0.1,3,2),IF(AND(E49<I49,OR(K49="Basso",K49="Bilaterale")),IF((I49-E49)/(J49-I49)>0.1,3,2),IF(M49="Borderline",1,0)))) -> 0 | P49: =N49*O49 -> 0 | Q49: Art.4 - Indici infiammatori | R49: Stesso limite della PCR con in piu una lentezza propria, perche misura una proprieta reologica del sangue che cambia nell'arco di giorni. Peso 0.
A50: 46 | B50: Rapporti cellulari | C50: Neutrofili / Linfociti (NLR) | D50: neutrofili / linfociti | E50: ='01 Input'!$B$48/'01 Input'!$B$47 -> 3.3712874 | F50: - | G50: 3.4 | H50: =IF(G50=0,"",(E50-G50)/ABS(G50)) -> -0.0084448785 | I50: 0.73 | J50: 3.33 | K50: Alto | L50: =IF(J50=I50,"",(E50-I50)/(J50-I50)) -> 1.0158798 | M50: =IF(E50>J50,"Fuori (alto)",IF(E50<I50,"Fuori (basso)",IF(AND(K50<>"Informativo",OR(AND(OR(K50="Alto",K50="Bilaterale"),L50>0.8),AND(OR(K50="Basso",K50="Bilaterale"),L50<0.2))),"Borderline","Normale"))) -> Fuori (alto) | N50: 2 | O50: =IF(N50=0,0,IF(AND(E50>J50,OR(K50="Alto",K50="Bilaterale")),IF((E50-J50)/(J50-I50)>0.1,3,2),IF(AND(E50<I50,OR(K50="Basso",K50="Bilaterale")),IF((I50-E50)/(J50-I50)>0.1,3,2),IF(M50="Borderline",1,0)))) -> 2 | P50: =N50*O50 -> 4 | Q50: Art.4 - Indici infiammatori | R50: L'infiammazione cronica sposta due popolazioni in direzioni opposte: alza l'immunita innata e abbassa i linfociti. Il rapporto cattura lo spostamento anche quando entrambi i valori assoluti restano dentro i loro intervalli, che e esattamente il caso qui (neutrofili 69% con limite 70, linfociti 20,5% con limite 20).
A51: 47 | B51: Rapporti cellulari | C51: Monociti / Linfociti (MLR) | D51: monociti / linfociti | E51: ='01 Input'!$B$49/'01 Input'!$B$47 -> 0.38001953 | F51: - | G51: 0.38 | H51: =IF(G51=0,"",(E51-G51)/ABS(G51)) -> 5.1400979e-05 | I51: 0.12 | J51: 0.38 | K51: Alto | L51: =IF(J51=I51,"",(E51-I51)/(J51-I51)) -> 1.0000751 | M51: =IF(E51>J51,"Fuori (alto)",IF(E51<I51,"Fuori (basso)",IF(AND(K51<>"Informativo",OR(AND(OR(K51="Alto",K51="Bilaterale"),L51>0.8),AND(OR(K51="Basso",K51="Bilaterale"),L51<0.2))),"Borderline","Normale"))) -> Fuori (alto) | N51: 2 | O51: =IF(N51=0,0,IF(AND(E51>J51,OR(K51="Alto",K51="Bilaterale")),IF((E51-J51)/(J51-I51)>0.1,3,2),IF(AND(E51<I51,OR(K51="Basso",K51="Bilaterale")),IF((I51-E51)/(J51-I51)>0.1,3,2),IF(M51="Borderline",1,0)))) -> 2 | P51: =N51*O51 -> 4 | Q51: Art.4 - Indici infiammatori | R51: Esattamente sul limite superiore, come la pressione diastolica dell'articolo 1. Il valore ricostruito lo supera di due centomillesimi, quindi il modello lo classifica come fuori e il conteggio coincide con i dieci dichiarati dalla fonte. E pero una posizione di equilibrio instabile: basta la terza cifra decimale dell'emocromo ricostruito per farlo ricadere dentro. Va letto come 'sulla soglia', non come 'oltre'.
A52: 48 | B52: Rapporti cellulari | C52: Piastrine / Linfociti (PLR) | D52: piastrine / linfociti | E52: ='01 Input'!$B$46/'01 Input'!$B$47 -> 156.25898 | F52: - | G52: 158 | H52: =IF(G52=0,"",(E52-G52)/ABS(G52)) -> -0.011019138 | I52: 63 | J52: 209 | K52: Alto | L52: =IF(J52=I52,"",(E52-I52)/(J52-I52)) -> 0.63876011 | M52: =IF(E52>J52,"Fuori (alto)",IF(E52<I52,"Fuori (basso)",IF(AND(K52<>"Informativo",OR(AND(OR(K52="Alto",K52="Bilaterale"),L52>0.8),AND(OR(K52="Basso",K52="Bilaterale"),L52<0.2))),"Borderline","Normale"))) -> Normale | N52: 1 | O52: =IF(N52=0,0,IF(AND(E52>J52,OR(K52="Alto",K52="Bilaterale")),IF((E52-J52)/(J52-I52)>0.1,3,2),IF(AND(E52<I52,OR(K52="Basso",K52="Bilaterale")),IF((I52-E52)/(J52-I52)>0.1,3,2),IF(M52="Borderline",1,0)))) -> 0 | P52: =N52*O52 -> 0 | Q52: Art.4 - Indici infiammatori | R52: Dentro l'intervallo. E uno dei sei indici che non segnalano nulla, e va registrato.
A53: 49 | B53: Indici compositi | C53: Systemic Inflammation Index (SII) | D53: piastrine x neutrofili / linfociti | E53: ='01 Input'!$B$46*'01 Input'!$B$48/'01 Input'!$B$47 -> 916.99018 | F53: - | G53: 917 | H53: =IF(G53=0,"",(E53-G53)/ABS(G53)) -> -1.0712796e-05 | I53: 131 | J53: 901 | K53: Alto | L53: =IF(J53=I53,"",(E53-I53)/(J53-I53)) -> 1.0207665 | M53: =IF(E53>J53,"Fuori (alto)",IF(E53<I53,"Fuori (basso)",IF(AND(K53<>"Informativo",OR(AND(OR(K53="Alto",K53="Bilaterale"),L53>0.8),AND(OR(K53="Basso",K53="Bilaterale"),L53<0.2))),"Borderline","Normale"))) -> Fuori (alto) | N53: 2 | O53: =IF(N53=0,0,IF(AND(E53>J53,OR(K53="Alto",K53="Bilaterale")),IF((E53-J53)/(J53-I53)>0.1,3,2),IF(AND(E53<I53,OR(K53="Basso",K53="Bilaterale")),IF((I53-E53)/(J53-I53)>0.1,3,2),IF(M53="Borderline",1,0)))) -> 2 | P53: =N53*O53 -> 4 | Q53: Art.4 - Indici infiammatori | R53: Combina le tre popolazioni in un solo numero. Appena oltre il limite superiore. Su 42.875 adulti seguiti per vent'anni SII e SIRI elevati risultano associati a mortalita totale e cardiovascolare (PMID 36769776).
A54: 50 | B54: Indici compositi | C54: Systemic Inflammation Response Index (SIRI) | D54: neutrofili x monociti / linfociti | E54: ='01 Input'!$B$48*'01 Input'!$B$49/'01 Input'!$B$47 -> 2.2301066 | F54: - | G54: 2.23 | H54: =IF(G54=0,"",(E54-G54)/ABS(G54)) -> 4.7813351e-05 | I54: 0 | J54: 0.68 | K54: Alto | L54: =IF(J54=I54,"",(E54-I54)/(J54-I54)) -> 3.2795686 | M54: =IF(E54>J54,"Fuori (alto)",IF(E54<I54,"Fuori (basso)",IF(AND(K54<>"Informativo",OR(AND(OR(K54="Alto",K54="Bilaterale"),L54>0.8),AND(OR(K54="Basso",K54="Bilaterale"),L54<0.2))),"Borderline","Normale"))) -> Fuori (alto) | N54: 3 | O54: =IF(N54=0,0,IF(AND(E54>J54,OR(K54="Alto",K54="Bilaterale")),IF((E54-J54)/(J54-I54)>0.1,3,2),IF(AND(E54<I54,OR(K54="Basso",K54="Bilaterale")),IF((I54-E54)/(J54-I54)>0.1,3,2),IF(M54="Borderline",1,0)))) -> 3 | P54: =N54*O54 -> 9 | Q54: Art.4 - Indici infiammatori | R54: Tre volte e mezzo la soglia. Insieme all'AISI e lo scostamento piu largo di tutto il workbook, in un uomo che sull'emocromo aveva un solo parametro fuori su ventisette.
A55: 51 | B55: Indici compositi | C55: Aggregate Index of Systemic Inflammation (AISI) | D55: neutrofili x monociti x piastrine / linfociti | E55: ='01 Input'!$B$48*'01 Input'!$B$49*'01 Input'!$B$46/'01 Input'!$B$47 -> 606.589 | F55: - | G55: 606.56 | H55: =IF(G55=0,"",(E55-G55)/ABS(G55)) -> 4.7813351e-05 | I55: 0 | J55: 147.16 | K55: Alto | L55: =IF(J55=I55,"",(E55-I55)/(J55-I55)) -> 4.1219693 | M55: =IF(E55>J55,"Fuori (alto)",IF(E55<I55,"Fuori (basso)",IF(AND(K55<>"Informativo",OR(AND(OR(K55="Alto",K55="Bilaterale"),L55>0.8),AND(OR(K55="Basso",K55="Bilaterale"),L55<0.2))),"Borderline","Normale"))) -> Fuori (alto) | N55: 3 | O55: =IF(N55=0,0,IF(AND(E55>J55,OR(K55="Alto",K55="Bilaterale")),IF((E55-J55)/(J55-I55)>0.1,3,2),IF(AND(E55<I55,OR(K55="Basso",K55="Bilaterale")),IF((I55-E55)/(J55-I55)>0.1,3,2),IF(M55="Borderline",1,0)))) -> 3 | P55: =N55*O55 -> 9 | Q55: Art.4 - Indici infiammatori | R55: Quattro volte la soglia. Su 23.765 ipertesi il quartile piu alto mostrava un rischio di mortalita cardiovascolare quasi doppio rispetto al piu basso, con hazard ratio 1,91 (PMID 37265570). Gli indici derivati dall'emocromo sono stati associati anche alla sarcopenia (PMID 38755603), che chiude il cerchio con l'articolo 2.
A56: 52 | B56: Rapporti misti | C56: Monociti / HDL | D56: monociti / HDL x 1000 | E56: ='01 Input'!$B$49/'01 Input'!$B$29*1000 -> 16.134146 | F56: per mille | G56: 16.1 | H56: =IF(G56=0,"",(E56-G56)/ABS(G56)) -> 0.0021208908 | I56: 0 | J56: 6 | K56: Alto | L56: =IF(J56=I56,"",(E56-I56)/(J56-I56)) -> 2.6890244 | M56: =IF(E56>J56,"Fuori (alto)",IF(E56<I56,"Fuori (basso)",IF(AND(K56<>"Informativo",OR(AND(OR(K56="Alto",K56="Bilaterale"),L56>0.8),AND(OR(K56="Basso",K56="Bilaterale"),L56<0.2))),"Borderline","Normale"))) -> Fuori (alto) | N56: 3 | O56: =IF(N56=0,0,IF(AND(E56>J56,OR(K56="Alto",K56="Bilaterale")),IF((E56-J56)/(J56-I56)>0.1,3,2),IF(AND(E56<I56,OR(K56="Basso",K56="Bilaterale")),IF((I56-E56)/(J56-I56)>0.1,3,2),IF(M56="Borderline",1,0)))) -> 3 | P56: =N56*O56 -> 9 | Q56: Art.4 - Indici infiammatori | R56: Quasi il triplo del limite. Le HDL non trasportano solo colesterolo: hanno una funzione antinfiammatoria diretta e ostacolano il reclutamento dei monociti nella parete arteriosa. Il rapporto mette in relazione chi accende l'infiammazione e chi dovrebbe spegnerla. Correlato a PCR, conta leucocitaria e ipertensione resistente (PMID 34109496). L'HDL a 41 dell'articolo 2 qui smette di essere un dettaglio.
A57: 53 | B57: Rapporti misti | C57: Emoglobina / RDW | D57: emoglobina / RDW | E57: ='01 Input'!$B$52/'01 Input'!$B$51 -> 0.95862069 | F57: - | G57: 0.96 | H57: =IF(G57=0,"",(E57-G57)/ABS(G57)) -> -0.0014367816 | I57: 1 | J57: 2 | K57: Basso | L57: =IF(J57=I57,"",(E57-I57)/(J57-I57)) -> -0.04137931 | M57: =IF(E57>J57,"Fuori (alto)",IF(E57<I57,"Fuori (basso)",IF(AND(K57<>"Informativo",OR(AND(OR(K57="Alto",K57="Bilaterale"),L57>0.8),AND(OR(K57="Basso",K57="Bilaterale"),L57<0.2))),"Borderline","Normale"))) -> Fuori (basso) | N57: 2 | O57: =IF(N57=0,0,IF(AND(E57>J57,OR(K57="Alto",K57="Bilaterale")),IF((E57-J57)/(J57-I57)>0.1,3,2),IF(AND(E57<I57,OR(K57="Basso",K57="Bilaterale")),IF((I57-E57)/(J57-I57)>0.1,3,2),IF(M57="Borderline",1,0)))) -> 2 | P57: =N57*O57 -> 4 | Q57: Art.4 - Indici infiammatori | R57: Sotto il valore minimo. Mette insieme quanta emoglobina c'e e quanto sono disomogenei i globuli rossi: cala quando il midollo produce eritrociti di taglia irregolare, che e il quadro dell'eritropoiesi ferro-ristretta dell'articolo 3.
A58: 54 | B58: Rapporti misti | C58: MPV / Linfociti | D58: volume piastrinico medio / linfociti | E58: ='01 Input'!$B$50/'01 Input'!$B$47 -> 6.8397771 | F58: - | G58: 6.84 | H58: =IF(G58=0,"",(E58-G58)/ABS(G58)) -> -3.2587549e-05 | I58: 0 | J58: 5.55 | K58: Alto | L58: =IF(J58=I58,"",(E58-I58)/(J58-I58)) -> 1.2323923 | M58: =IF(E58>J58,"Fuori (alto)",IF(E58<I58,"Fuori (basso)",IF(AND(K58<>"Informativo",OR(AND(OR(K58="Alto",K58="Bilaterale"),L58>0.8),AND(OR(K58="Basso",K58="Bilaterale"),L58<0.2))),"Borderline","Normale"))) -> Fuori (alto) | N58: 1 | O58: =IF(N58=0,0,IF(AND(E58>J58,OR(K58="Alto",K58="Bilaterale")),IF((E58-J58)/(J58-I58)>0.1,3,2),IF(AND(E58<I58,OR(K58="Basso",K58="Bilaterale")),IF((I58-E58)/(J58-I58)>0.1,3,2),IF(M58="Borderline",1,0)))) -> 3 | P58: =N58*O58 -> 3 | Q58: Art.4 - Indici infiammatori | R58: Il volume piastrinico medio sale quando il midollo rilascia piastrine piu giovani e reattive, ed e un marcatore di attivazione piastrinica nell'infiammazione (PMID 31148950).
A59: 55 | B59: Rapporti misti | C59: MPV / Piastrine | D59: MPV / piastrine x 100 | E59: ='01 Input'!$B$50/'01 Input'!$B$46*100 -> 4.3772059 | F59: - | G59: 4.3 | H59: =IF(G59=0,"",(E59-G59)/ABS(G59)) -> 0.017954856 | I59: 0 | J59: 4 | K59: Alto | L59: =IF(J59=I59,"",(E59-I59)/(J59-I59)) -> 1.0943015 | M59: =IF(E59>J59,"Fuori (alto)",IF(E59<I59,"Fuori (basso)",IF(AND(K59<>"Informativo",OR(AND(OR(K59="Alto",K59="Bilaterale"),L59>0.8),AND(OR(K59="Basso",K59="Bilaterale"),L59<0.2))),"Borderline","Normale"))) -> Fuori (alto) | N59: 1 | O59: =IF(N59=0,0,IF(AND(E59>J59,OR(K59="Alto",K59="Bilaterale")),IF((E59-J59)/(J59-I59)>0.1,3,2),IF(AND(E59<I59,OR(K59="Basso",K59="Bilaterale")),IF((I59-E59)/(J59-I59)>0.1,3,2),IF(M59="Borderline",1,0)))) -> 2 | P59: =N59*O59 -> 2 | Q59: Art.4 - Indici infiammatori | R59: Appena oltre la soglia. Descrive lo stesso fenomeno del precedente rapportato alla massa piastrinica totale.
A60: 56 | B60: Rapporti misti | C60: RDW / Piastrine | D60: RDW / piastrine | E60: ='01 Input'!$B$51/'01 Input'!$B$46 -> 0.053308824 | F60: - | G60: 0.05 | H60: =IF(G60=0,"",(E60-G60)/ABS(G60)) -> 0.066176471 | I60: 0 | J60: 0.07 | K60: Alto | L60: =IF(J60=I60,"",(E60-I60)/(J60-I60)) -> 0.76155462 | M60: =IF(E60>J60,"Fuori (alto)",IF(E60<I60,"Fuori (basso)",IF(AND(K60<>"Informativo",OR(AND(OR(K60="Alto",K60="Bilaterale"),L60>0.8),AND(OR(K60="Basso",K60="Bilaterale"),L60<0.2))),"Borderline","Normale"))) -> Normale | N60: 1 | O60: =IF(N60=0,0,IF(AND(E60>J60,OR(K60="Alto",K60="Bilaterale")),IF((E60-J60)/(J60-I60)>0.1,3,2),IF(AND(E60<I60,OR(K60="Basso",K60="Bilaterale")),IF((I60-E60)/(J60-I60)>0.1,3,2),IF(M60="Borderline",1,0)))) -> 0 | P60: =N60*O60 -> 0 | Q60: Art.4 - Indici infiammatori | R60: Dentro la soglia. E pubblicato con due sole cifre decimali, il che lascia molta indeterminazione: e da questa riga che dipende la ricostruzione di RDW ed emoglobina nel foglio 01.
A61: 57 | B61: Metabolici | C61: Omocisteina | D61: misurata | E61: ='01 Input'!$B$42 -> 14.6 | F61: uM | G61: 14.6 | H61: =IF(G61=0,"",(E61-G61)/ABS(G61)) -> 0 | I61: 3 | J61: 15 | K61: Alto | L61: =IF(J61=I61,"",(E61-I61)/(J61-I61)) -> 0.96666667 | M61: =IF(E61>J61,"Fuori (alto)",IF(E61<I61,"Fuori (basso)",IF(AND(K61<>"Informativo",OR(AND(OR(K61="Alto",K61="Bilaterale"),L61>0.8),AND(OR(K61="Basso",K61="Bilaterale"),L61<0.2))),"Borderline","Normale"))) -> Borderline | N61: 2 | O61: =IF(N61=0,0,IF(AND(E61>J61,OR(K61="Alto",K61="Bilaterale")),IF((E61-J61)/(J61-I61)>0.1,3,2),IF(AND(E61<I61,OR(K61="Basso",K61="Bilaterale")),IF((I61-E61)/(J61-I61)>0.1,3,2),IF(M61="Borderline",1,0)))) -> 1 | P61: =N61*O61 -> 2 | Q61: Art.4 - Indici infiammatori | R61: Dentro l'intervallo largo per quattro decimi, ma il doppio del limite superiore della finestra ottimale (5,0-7,2) indicata dalla stessa tabella. E il divario piu ampio fra riferimento tollerato e riferimento desiderabile di tutto il workbook.
A62: 58 | B62: Metabolici | C62: Uricemia | D62: misurata | E62: ='01 Input'!$B$43 -> 6.7 | F62: mg/dL | G62: 6.7 | H62: =IF(G62=0,"",(E62-G62)/ABS(G62)) -> 0 | I62: 3.5 | J62: 7.2 | K62: Alto | L62: =IF(J62=I62,"",(E62-I62)/(J62-I62)) -> 0.86486486 | M62: =IF(E62>J62,"Fuori (alto)",IF(E62<I62,"Fuori (basso)",IF(AND(K62<>"Informativo",OR(AND(OR(K62="Alto",K62="Bilaterale"),L62>0.8),AND(OR(K62="Basso",K62="Bilaterale"),L62<0.2))),"Borderline","Normale"))) -> Borderline | N62: 2 | O62: =IF(N62=0,0,IF(AND(E62>J62,OR(K62="Alto",K62="Bilaterale")),IF((E62-J62)/(J62-I62)>0.1,3,2),IF(AND(E62<I62,OR(K62="Basso",K62="Bilaterale")),IF((I62-E62)/(J62-I62)>0.1,3,2),IF(M62="Borderline",1,0)))) -> 1 | P62: =N62*O62 -> 2 | Q62: Art.4 - Indici infiammatori | R62: Dentro l'intervallo largo, ben oltre la finestra ottimale (2,5-4,0). L'acido urico e a sua volta un promotore di infiammazione e di disfunzione endoteliale.
A63: 59 | B63: Metabolici | C63: Uricemia / HDL | D63: uricemia / HDL x 100 | E63: ='01 Input'!$B$43/'01 Input'!$B$29*100 -> 16.341463 | F63: - | G63: 16.3 | H63: =IF(G63=0,"",(E63-G63)/ABS(G63)) -> 0.0025437678 | I63: 0 | J63: 12.2 | K63: Alto | L63: =IF(J63=I63,"",(E63-I63)/(J63-I63)) -> 1.3394642 | M63: =IF(E63>J63,"Fuori (alto)",IF(E63<I63,"Fuori (basso)",IF(AND(K63<>"Informativo",OR(AND(OR(K63="Alto",K63="Bilaterale"),L63>0.8),AND(OR(K63="Basso",K63="Bilaterale"),L63<0.2))),"Borderline","Normale"))) -> Fuori (alto) | N63: 2 | O63: =IF(N63=0,0,IF(AND(E63>J63,OR(K63="Alto",K63="Bilaterale")),IF((E63-J63)/(J63-I63)>0.1,3,2),IF(AND(E63<I63,OR(K63="Basso",K63="Bilaterale")),IF((I63-E63)/(J63-I63)>0.1,3,2),IF(M63="Borderline",1,0)))) -> 3 | P63: =N63*O63 -> 6 | Q63: Art.4 - Indici infiammatori | R63: Un terzo sopra il cut-off. Come il rapporto monociti/HDL, deve il suo valore tanto al numeratore alto quanto al denominatore basso: l'HDL a 41 compare come denominatore in due dei tre indici piu alterati di questa sezione.
C65: TOTALE PUNTEGGIO STRUMENTALE (entrambe le fonti) | N65: =SUM(N5:N63) -> 91 | P65: =SUM(P5:P63) -> 170

Sheet 03 Formule
A1: 03 - Dizionario delle formule
A2: Le formule marcate 'Ricostruita' non sono scritte per esteso nelle fonti: sono state ricavate cercando l'espressione che riproduce il valore pubblicato dai dati grezzi noti.
A4: # | B4: Fonte | C4: Grandezza | D4: Formula | E4: Verifica sul caso | F4: Origine | G4: Nota metodologica
A5: 1 | B5: Art.1 | C5: Pressione arteriosa media | D5: MAP = DBP + 0,4 x (SBP - DBP) | E5: 84 + 0,4x44 = 101,6 -> 101 | F5: Ricostruita | G5: La formula classica (SBP + 2xDBP)/3 restituisce 98,7 e NON riproduce il valore pubblicato. Il coefficiente 0,4 al posto di 1/3 tiene conto dell'accorciamento della diastole. Chi ricalcola con la classica ottiene un Modified Shock Index di 0,83 invece di 0,81.
A6: 2 | B6: Art.1 | C6: Pressione di pulsazione | D6: PP = SBP - DBP | E6: 128 - 84 = 44 | F6: Esplicita | G6: Cresce quando l'aorta perde elasticita e smette di ammortizzare l'onda sistolica.
A7: 3 | B7: Art.1 | C7: FC massima - formula popolare | D7: FCmax = 220 - eta | E7: 220 - 50 = 170 | F7: Citata come errata | G7: Sottostima la FC massima negli adulti maturi. E la formula che fa sospettare un errore a chi verifica il referto.
A8: 4 | B8: Art.1 | C8: FC massima - Tanaka | D8: FCmax = 208 - 0,7 x eta | E8: 208 - 35 = 173 | F8: PMID 11153730 | G8: Meta-analisi su 351 studi e 18.712 soggetti. Migliora la stima ma resta lineare, quindi applica lo stesso decadimento a ogni eta.
A9: 5 | B9: Art.1 | C9: FC massima - modello del referto | D9: modello logistico sesso-specifico | E9: 175 (da referto) | F9: PMID 12752560 / 11722475 | G9: Tarato su cicloergometro fino a esaurimento. Decadimento non costante: 0,43 bpm/anno a 25 anni, 0,83 a 50, 1,35 a 75. Coefficienti non pubblicati.
A10: 6 | B10: Art.1 | C10: FC di riserva | D10: FCris = FCmax - FCriposo | E10: 175 - 82 = 93 | F10: Esplicita | G10: Migliora abbassando il basale, cioe senza che il cuore cambi davvero: e un artefatto da tenere presente.
A11: 7 | B11: Art.1 | C11: Modified Shock Index | D11: MSI = FCriposo / MAP | E11: 82 / 101 = 0,81 | F11: Esplicita | G11: La fonte segnala l'errore diffuso di usare la sistolica al denominatore: 82/128 darebbe 0,64.
A12: 8 | B12: Art.1 | C12: Prodotto cardiovascolare | D12: RPP = FCriposo x SBP | E12: 82 x 128 = 10.496 | F12: Esplicita / PMID 38453019 | G12: Rate pressure product, surrogato del consumo miocardico di ossigeno.
A13: 9 | B13: Art.1 | C13: Portata cardiaca | D13: CO = SV x FC | E13: 66 x 82 = 5.412 mL/min | F13: Esplicita | G13: Lo stesso output si ottiene con SV 80 mL e FC 68: la portata normale non distingue una pompa capiente lenta da una piccola veloce.
A14: 10 | B14: Art.1 | C14: Cardiac Index | D14: CI = CO / BSA | E14: 5,412 / 1,9 = 2,85 -> 2,8 | F14: Esplicita | G14: Portata indicizzata per superficie corporea.
A15: 11 | B15: Art.1 | C15: Left Cardiac Work Index | D15: LCWI = CI x MAP x 2,222 | E15: 2,8 x 101 x 2,222 = 628 (referto 627) | F15: Ricostruita | G15: La costante converte L/min x mmHg in milliwatt: 1 L/min = 1,6667e-5 m3/s e 1 mmHg = 133,322 Pa, prodotto 2,222 mW. Con il CI e la MAP non arrotondati si ottengono 643, circa il 2,6% sopra il pubblicato.
A16: 12 | B16: Art.1 | C16: Indice di rigidita arteriosa | D16: ASI = PP / MAP | E16: 44 / 101 = 0,436 -> 0,44 | F16: Ricostruita | G16: Il rapporto alternativo PP/SBP darebbe 0,34 e non riproduce il referto.
... A56: 52 | B56: Art.4 | C56: Ricostruzione dell'emocromo | D56: piastrine = AISI/SIRI; monociti = AISI/SII; linfociti = monociti/MLR; neutrofili = SIRI x linfociti / monociti | E56: P 272; M 0,662; L 1,741; N 5,868 | F56: Inversione degli indici | G56: L'articolo non pubblica i conteggi assoluti, ma il sistema di sei indici in quattro incognite e sovradeterminato e si risolve. La verifica incrociata restituisce SII, SIRI, AISI e MLR esatti, NLR entro lo 0,8% e PLR entro l'1,1%.

Sheet 04 Zone FC
A1: 04 - Zone di frequenza cardiaca
A2: Ricavate dalla FC massima del foglio 01. Le soglie si ottengono troncando all'intero la percentuale della FC massima.
A4: Zona | B4: Obiettivo | C4: % min | D4: % max | E4: Da (bpm) | F4: A (bpm) | G4: Nota
A5: 0 | B5: Riposo | C5: 0 | D5: 0.5 | E5: 0 | F5: =INT(C6*'01 Input'!$B$25)-1 -> 86 | G5: Zona in cui si trova il soggetto a riposo.
A6: 1 | B6: Attivita moderata | C6: 0.5 | D6: 0.6 | E6: =INT(C6*'01 Input'!$B$25) -> 87 | F6: =INT(C7*'01 Input'!$B$25)-1 -> 104 | G6: Il limite inferiore e il confine che il soggetto sfiora da fermo.
A7: 2 | B7: Controllo del peso | C7: 0.6 | D7: 0.7 | E7: =INT(C7*'01 Input'!$B$25) -> 105 | F7: =INT(C8*'01 Input'!$B$25)-1 -> 121
A8: 3 | B8: Aerobiosi | C8: 0.7 | D8: 0.8 | E8: =INT(C8*'01 Input'!$B$25) -> 122 | F8: =INT(C9*'01 Input'!$B$25)-1 -> 139
A9: 4 | B9: Anaerobiosi | C9: 0.8 | D9: 0.9 | E9: =INT(C9*'01 Input'!$B$25) -> 140 | F9: =INT(C10*'01 Input'!$B$25)-1 -> 156
A10: 5 | B10: Massimale | C10: 0.9 | D10: 1 | E10: =INT(C10*'01 Input'!$B$25) -> 157 | F10: ='01 Input'!$B$25 -> 175 | G10: Da leggere con la tolleranza del 90-110% sulla FC massima predetta.
B12: FC a riposo del soggetto | E12: ='01 Input'!$B$23 -> 82
B13: Soglia di uscita dalla zona 0 | E13: =E6 -> 87
B14: Margine residuo prima di uscire dal riposo | E14: =E13-E12 -> 5 | G14: Battiti che separano il soggetto, da fermo, dalla zona dell'attivita moderata.

Sheet 05 Evidenze
A1: 05 - Evidenze citate dalle fonti
A2: Ogni riga riporta la misura di rischio come pubblicata e la sua applicabilita al caso in esame.
A4: # | B4: Fonte | C4: PMID | D4: Studio / disegno | E4: Numerosita | F4: Esposizione | G4: Misura | H4: Esito | I4: Applicabilita al caso
A5: 1 | B5: Art.1 | C5: 26598376 | D5: Meta-analisi di 46 studi prospettici | E5: 1.246.203 soggetti / 78.349 decessi | F5: FC a riposo, per ogni +10 bpm | G5: RR 1,09 | H5: Mortalita totale | I5: Il soggetto e a 82 bpm: 17 bpm oltre la fascia di minimo, circa +16% di rischio relativo per estrapolazione.
A6: 2 | B6: Art.1 | C6: 26598376 | D6: Meta-analisi - analisi per categorie | E6: 1.246.203 soggetti | F6: FC a riposo > 80 bpm | G6: RR 1,45 | H6: Mortalita totale | I6: SOGLIA SUPERATA (82 bpm). E il salto di scala descritto dalla fonte.
A7: 3 | B7: Art.1 | C7: 26598376 | D7: Meta-analisi - analisi per categorie | E7: 1.246.203 soggetti | F7: FC a riposo > 80 bpm | G7: RR 1,33 | H7: Mortalita cardiovascolare | I7: Soglia superata.
A8: 4 | B8: Art.1 | C8: 11337213 | D8: Coorte giapponese, 18 anni | E8: 573 uomini, 40-64 anni | F8: FC > 90 vs 60-69 bpm | G8: RR 2,68 | H8: Mortalita | I8: Il minimo di mortalita cade fra 60 e 69 bpm e l'aumento comincia ben prima dei 90: il soggetto e nel tratto ascendente.
A9: 5 | B9: Art.1 | C9: 28067310 | D9: Coorte di Kailuan, 3 misurazioni in 4 anni | E9: 47.311 adulti | F9: FC >= 80 bpm in tutte e tre le misurazioni | G9: HR 1,86 | H9: Mortalita per ogni causa | I9: Lo studio piu pertinente perche misura la persistenza. Applicabile solo se il valore viene confermato nel tempo: servono misurazioni ripetute.
A10: 6 | B10: Art.1 | C10: 17446799 | D10: Coorte prospettica, 5 anni | E10: 1.910 uomini | F10: Riserva impegnata sotto l'80% | G10: HR 2,8 | H10: Mortalita cardiovascolare | I10: NON VALUTABILE: richiede un test da sforzo che il referto non contiene. E il principale accertamento mancante.
A11: 7 | B11: Art.1 | C11: 10353296 | D11: Revisione (Palatini) sull'ipertono simpatico | E11: - | F11: Tachicardia cronica | G11: - | H11: Meccanismo | I11: Doppio meccanismo: marcatore di iperattivita adrenergica e stimolo meccanico diretto, con stress di parete che favorisce la placca.
A12: 8 | B12: Art.1 | C12: 33793325 | D12: Revisione su Circulation Research | E12: - | F12: Pressione di pulsazione elevata | G12: - | H12: Invecchiamento vascolare | I12: La pulsatilita si scarica su cervello e rene e riduce la diastolica utile alla perfusione coronarica. Il soggetto e dentro il range.
A13: 9 | B13: Art.1 | C13: 38453019 | D13: Letteratura sul rate pressure product | E13: - | F13: Prodotto cardiovascolare | G13: - | H13: Consumo miocardico di O2 | I13: Valida il prodotto cardiovascolare come surrogato non invasivo del consumo miocardico di ossigeno.
A14: 10 | B14: Art.1 | C14: 35328926 | D14: Effetti acuti del fumo | E14: giovani normotesi | F14: Singola sigaretta | G14: - | H14: Aumento acuto di MAP e FC | I14: Effetto acuto: su un referto a riposo conta poco. Rileva cio che resta fra una sigaretta e l'altra.
A15: 11 | B15: Art.1 | C15: 8689656 | D15: Caso-controllo su variabilita RR | E15: 20 fumatori > 20 sig/die vs controlli | F15: Fumo abituale | G15: LF 70,6 vs 46,0; HF 22,1 vs 42,0 | H15: Assetto autonomico spostato | I15: APPLICABILE: il soggetto fuma 20 sigarette al giorno. Piu acceleratore simpatico, meno freno vagale. Parte dei battiti in eccesso viene da qui.
A16: 12 | B16: Art.1 | C16: 16029383 | D16: Studio su forti fumatori | E16: - | F16: Durata dell'abitudine | G16: - | H16: Calo della modulazione vagale | I16: APPLICABILE E PIU PERTINENTE: misura gli anni, non solo le sigarette. Il soggetto ne ha 30.
... A43: 39 | B43: Art.4 | C43: 12160596 | D43: Studio metodologico (Van Tiel) | E43: - | F43: VES | G43: - | H43: Limiti interpretativi | I43: Sostiene il ridimensionamento della VES come strumento per l'infiammazione cronica di basso grado.

Sheet 06 Rischio
A1: 06 - Valutazione della pericolosita
A2: Tre letture indipendenti: il punteggio strumentale dagli indici delle due fonti, i fattori anamnestici che i referti non contengono e il rischio relativo epidemiologico.
B4: A - PUNTEGGIO STRUMENTALE (59 indici, quattro fonti)
B5: Indici valutati in totale | C5: =COUNT('02 Indici'!$O$5:$O$63) -> 59 | G5: Righe presenti nel foglio 02.
B6: Indici normali | C6: =COUNTIF('02 Indici'!$M$5:$M$63,"Normale") -> 22
B7: Indici borderline (in zona di guardia) | C7: =COUNTIF('02 Indici'!$M$5:$M$63,"Borderline") -> 12 | G7: Dentro l'intervallo ma nell'ultimo 20% verso il lato critico. I referti li stampano come normali.
B8: Indici fuori intervallo | C8: =COUNTIF('02 Indici'!$M$5:$M$63,"Fuori (alto)")+COUNTIF('02 Indici'!$M$5:$M$63,"Fuori (basso)") -> 25
B9: di cui dall'articolo 1 (cardiologici) | C9: =COUNTIFS('02 Indici'!$Q$5:$Q$63,"Art.1*",'02 Indici'!$M$5:$M$63,"Fuori (alto)")+COUNTIFS('02 Indici'!$Q$5:$Q$63,"Art.1*",'02 Indici'!$M$5:$M$63,"Fuori (basso)") -> 1 | G9: La fonte dichiara 1 indice fuori range su 16.
B10: di cui dall'articolo 2 (antropometrici) | C10: =COUNTIFS('02 Indici'!$Q$5:$Q$63,"Art.2*",'02 Indici'!$M$5:$M$63,"Fuori (alto)")+COUNTIFS('02 Indici'!$Q$5:$Q$63,"Art.2*",'02 Indici'!$M$5:$M$63,"Fuori (basso)") -> 8 | G10: La fonte dichiara 6 indici oltre soglia su 12; applicando i cut-off delle sue stesse tabelle ne risultano 9. Vedi foglio 08.
B11: di cui dall'articolo 3 (profilo marziale) | C11: =COUNTIFS('02 Indici'!$Q$5:$Q$63,"Art.3*",'02 Indici'!$M$5:$M$63,"Fuori (alto)")+COUNTIFS('02 Indici'!$Q$5:$Q$63,"Art.3*",'02 Indici'!$M$5:$M$63,"Fuori (basso)") -> 6 | G11: La fonte dichiara 5 valori fuori dalle finestre ottimali su 11; applicando gli intervalli della sua stessa tabella ne risultano 6. Vedi foglio 08.
B12: di cui dall'articolo 4 (infiammatori) | C12: =COUNTIFS('02 Indici'!$Q$5:$Q$63,"Art.4*",'02 Indici'!$M$5:$M$63,"Fuori (alto)")+COUNTIFS('02 Indici'!$Q$5:$Q$63,"Art.4*",'02 Indici'!$M$5:$M$63,"Fuori (basso)") -> 10 | G12: La fonte dichiara 10 indici fuori riferimento su 16 e il conteggio coincide, ma il decimo (monociti/linfociti) sta esattamente sul limite: e il solo caso in cui la classificazione dipende dall'ultima cifra decimale.
B13: Punteggio ponderato ottenuto | C13: =SUM('02 Indici'!$P$5:$P$63) -> 170 | G13: Somma di peso clinico x punteggio 0-3.
B14: Punteggio massimo teorico | C14: =SUM('02 Indici'!$N$5:$N$63)*3 -> 273 | G14: Se ogni indice pesato fosse gravemente fuori range.
B15: COMPONENTE STRUMENTALE | C15: =IF(C14=0,0,C13/C14) -> 0.62271062 | G15: Quota del massimo teorico raggiunta.
B17: B - FATTORI ANAMNESTICI E PATTERN CHE I SINGOLI INDICI NON ESPRIMONO
B18: Fattore | C18: Presente | D18: Peso | E18: Punti | G18: Evidenza / nota
B19: Fumo attivo (>= 20 sigarette al giorno) | C19: =IF('01 Input'!$B$58>=20,1,0) -> 1 | D19: 3 | E19: =C19*D19 -> 3 | G19: PMID 8689656 - assetto autonomico spostato verso il simpatico anche a distanza dall'ultima sigaretta.
B20: Durata dell'abitudine tabagica >= 20 anni | C20: =IF('01 Input'!$B$59>=20,1,0) -> 1 | D20: 2 | E20: =C20*D20 -> 2 | G20: PMID 16029383 - la modulazione vagale cala al crescere degli anni, non solo delle sigarette.
B21: Fenotipo TOFI (normopeso con obesita centrale) | C21: =IF(AND('02 Indici'!$E21<25,'02 Indici'!$E$25>0.5),1,0) -> 1 | D21: 3 | E21: =C21*D21 -> 3 | G21: PMID 26551006 - calcolato dagli indici: BMI sotto 25 con vita oltre meta dell'altezza. La mortalita cardiovascolare supera quella dell'obeso con distribuzione periferica.
B22: Miosteatosi documentata | C22: ='01 Input'!$B$60 -> 1 | D22: 2 | E22: =C22*D22 -> 2 | G22: PMID 35227529 - infiltrazione adiposa del muscolo, non misurabile con l'antropometria di superficie. Un quadricipite infiltrato pesa uguale e lavora peggio.
B23: Sospetta apnea ostruttiva del sonno mai indagata | C23: ='01 Input'!$B$61 -> 1 | D23: 3 | E23: =C23*D23 -> 3 | G23: PMID 15301332 e 12609010 - il tono simpatico resta elevato anche in veglia. E il sospetto piu pesante proprio perche non e mai stato verificato.
B24: Sedentarieta | C24: ='01 Input'!$B$62 -> 1 | D24: 1 | E24: =C24*D24 -> 1 | G24: PMID 15793048 - l'esercizio supervisionato abbassa del 19% il prodotto cardiovascolare; la sua assenza toglie il principale fattore correttivo.
B25: Incremento ponderale > 5 kg dall'eta di 30 anni | C25: =IF('01 Input'!$B$11-'01 Input'!$B$17>5,1,0) -> 1 | D25: 1 | E25: =C25*D25 -> 1 | G25: Sei chili in vent'anni, trecento grammi l'anno: l'aumento piu banale del mondo. Sotto, circa dieci chili di grasso in piu e quattro di muscolo in meno.
B26: Pattern di eritropoiesi ferro-ristretta | C26: =IF(AND('02 Indici'!$E$42<20,'02 Indici'!$E$46>301.5),1,0) -> 1 | D26: 3 | E26: =C26*D26 -> 3 | G26: PMID 30401705 - calcolato dagli indici: saturazione sotto il 20% con depositi non esauriti. Il ferro c'e ma non arriva ai reticolociti. Nessuna singola riga del profilo marziale lo dice: emerge solo dalla combinazione.
B27: Infiammazione cronica di basso grado con indici classici negativi | C27: =IF(AND('02 Indici'!$E$48<=0.5,COUNTIFS('02 Indici'!$Q$5:$Q$63,"Art.4*",'02 Indici'!$M$5:$M$63,"Fuori (alto)")+COUNTIFS('02 Indici'!$Q$5:$Q$63,"Art.4*",'02 Indici'!$M$5:$M$63,"Fuori (basso)")>=5),1,0) -> 1 | D27: 3 | E27: =C27*D27 -> 3 | G27: PMID 36769776 e 37265570 - calcolato: PCR normale con almeno cinque indici derivati oltre soglia. E la condizione che rende non verificabile l'aggiustamento per infiammazione dell'articolo 3 e che al tempo stesso lo giustifica sul piano fisiopatologico.
B28: Punti ottenuti | C28: =SUMPRODUCT(C19:C27,D19:D27) -> 21
B29: Punti massimi | C29: =SUM(D19:D27) -> 21
B30: COMPONENTE ANAMNESTICA | C30: =IF(C29=0,0,C28/C29) -> 1 | G30: La sarcopenia non compare qui perche e gia misurata fra gli indici del foglio 02, per evitare di contarla due volte.
B32: C - RISCHIO EPIDEMIOLOGICO CALCOLATO
B33: Scostamento dalla FC di minimo rischio (60-69 bpm) | C33: ='01 Input'!$B$23-'01 Input'!$B$65 -> 17 | G33: bpm oltre il punto medio della fascia con mortalita minima.
B34: Scostamento dal limite superiore del referto | C34: ='01 Input'!$B$23-'01 Input'!$B$67 -> 6 | G34: bpm oltre il valore che il referto considera normale.
B35: RR mortalita totale (+1,09 ogni 10 bpm) | C35: =1.09^(('01 Input'!$B$23-'01 Input'!$B$65)/10) -> 1.1577773 | G35: PMID 26598376. Stima di gradiente, non rischio assoluto individuale.
B36: RR mortalita cardiovascolare (+1,08 ogni 10 bpm) | C36: =1.08^(('01 Input'!$B$23-'01 Input'!$B$65)/10) -> 1.1397783 | G36: PMID 26598376.
B37: Soglia FC > 80 bpm superata | C37: =IF('01 Input'!$B$23>'01 Input'!$B$66,"SI","NO") -> SI | G37: Oltre gli 80 bpm il quadro cambia scala: RR 1,45 totale e 1,33 cardiovascolare.
B38: RR categoriale - mortalita totale | C38: =IF('01 Input'!$B$23>'01 Input'!$B$66,1.45,"n.a.") -> 1.45 | G38: PMID 26598376.
B39: RR categoriale - mortalita cardiovascolare | C39: =IF('01 Input'!$B$23>'01 Input'!$B$66,1.33,"n.a.") -> 1.33 | G39: PMID 26598376.
B40: HR se il valore >= 80 bpm si conferma nel tempo | C40: =IF('01 Input'!$B$23>='01 Input'!$B$66,1.86,"n.a.") -> 1.86 | G40: PMID 28067310. Richiede misurazioni ripetute, oggi non disponibili.
B41: Battiti in eccesso all'anno | C41: =('01 Input'!$B$23-'01 Input'!$B$67)*60*24*365 -> 3153600 | G41: Il carico cumulativo che nessun sintomo segnala e nessuna visita registra.
B42: Battiti in eccesso in 10 anni | C42: =('01 Input'!$B$23-'01 Input'!$B$67)*60*24*365*10 -> 31536000
B43: Criterio vita per sindrome metabolica | C43: =IF('01 Input'!$B$13>='01 Input'!$B$68,"SODDISFATTO","NON soddisfatto") -> NON soddisfatto | G43: Il criterio binario resta vuoto per 4 cm, mentre vita/altezza, conicita e ABSI sono gia tutti oltre i rispettivi cut-off. E il limite delle soglie a interruttore su variabili continue.
B44: Centimetri di vita che mancano al criterio | C44: ='01 Input'!$B$68-'01 Input'!$B$13 -> 4
B46: D - INDICE COMPOSITO DI PERICOLOSITA
B47: Peso della componente strumentale | C47: 0.6 | G47: Modificabile: le due componenti devono sommare a 1.
B48: Peso della componente anamnestica | C48: =1-C47 -> 0.4 | G48: I referti coprono la maggior parte del giudizio, ma non tutto: il resto viene da cio che non misurano.
B49: PUNTEGGIO DI PERICOLOSITA (0-100) | C49: =(C15*C47+C30*C48)*100 -> 77.362637 | G49: Media pesata delle due componenti su scala centesimale.
B50: FASCIA | C50: =IF(C49<20,"BASSO",IF(C49<40,"LIEVE",IF(C49<60,"MODERATO",IF(C49<80,"ELEVATO","ALTO")))) -> ELEVATO | G50: Fasce: <20 basso | 20-40 lieve | 40-60 moderato | 60-80 elevato | >=80 alto.
B52: Lettura sintetica | C52: ="Su "&C5&" indici ricalcolati, "&C8&" risultano fuori intervallo nella direzione critica e "&C7&" sono in zona di guardia pur essendo stampati come normali. "&IF('01 Input'!$B$23>'01 Input'!$B$66,"La frequenza a riposo supera la soglia degli 80 bpm, oltre la quale il rischio cambia scala. ","")&IF(AND('02 Indici'!$E21<25,'02 Indici'!$E$25>0.5),"Il BMI resta sotto 25 mentre la vita supera la meta dell altezza: e il fenotipo che il peso corporeo nasconde. ","")&IF(AND('02 Indici'!$E$42<20,'02 Indici'!$E$46>301.5),"Il profilo marziale mostra saturazione bassa con depositi non esauriti: il ferro c e ma non arriva dove serve, quindi la sola supplementazione marziale sarebbe verosimilmente inefficace e la leva utile e la causa infiammatoria. ","")&IF('02 Indici'!$E$48<=0.5,"I due indici infiammatori classici sono negativi, ma gli indici derivati dall emocromo documentano infiammazione cronica di basso grado: SIRI a "&TEXT('02 Indici'!$E$54,"0.00")&" contro 0,68 e AISI a "&TEXT('02 Indici'!$E$55,"0")&" contro 147. ","")&"Fattori anamnestici e pattern presenti: "&C28&" punti su "&C29&". "&"Accertamenti mancanti che cambierebbero il giudizio: test da sforzo, studio del sonno, misurazioni ripetute della frequenza, marcatori di infiammazione e contenuto emoglobinico reticolocitario." -> Su 59 indici ricalcolati, 25 risultano fuori intervallo nella direzione critica e 12 sono in zona di guardia pur essendo stampati come normali. La frequenza a riposo supera la soglia degli 80 bpm, oltre la quale il rischio cambia scala. Il BMI resta sotto 25 mentre la vita supera la meta dell altezza: e il fenotipo che il peso corporeo nasconde. Il profilo marziale mostra saturazione bassa con depositi non esauriti: il ferro c e ma non arriva dove serve, quindi la sola supplementazione marziale sarebbe verosimilmente inefficace e la leva utile e la causa infiammatoria. I due indici infiammatori classici sono negativi, ma gli indici derivati dall emocromo documentano infiammazione cronica di basso grado: SIRI a 2.23 contro 0,68 e AISI a 607 contro 147. Fattori anamnestici e pattern presenti: 21 punti su 21. Accertamenti mancanti che cambierebbero il giudizio: test da sforzo, studio del sonno, misurazioni ripetute della frequenza, marcatori di infiammazione e contenuto emoglobinico reticolocitario.
B57: E - COSA I REFERTI NON POSSONO DIRE
B58: Test da sforzo | C58: Senza di esso non e valutabile la riserva effettivamente impegnata, il parametro con HR 2,8 per mortalita cardiovascolare (PMID 17446799).
B59: Studio del sonno | C59: Russamento e pause respiratorie riferiti ma mai indagati. Le apnee spiegherebbero una quota della frequenza elevata (PMID 15301332).
B60: Misurazioni ripetute della FC a riposo | C60: L'HR 1,86 di Kailuan si applica alla persistenza del valore su piu misurazioni, non a un singolo prelievo (PMID 28067310).
B61: Variabilita della frequenza cardiaca (HRV) | C61: LF, HF e guadagno barocettivo sono i parametri su cui il fumo agisce, e nessuno di essi compare nei referti.
B62: Glicemia, insulinemia, enzimi epatici | C62: VAI e CMI segnalano resistenza insulinica e disfunzione del tessuto adiposo, ma la conferma diretta richiede i marcatori di sensibilita insulinica e di steatosi.
B63: DEXA o bioimpedenziometria | C63: Gli indici antropometrici stratificano il rischio a costo quasi nullo, ma non quantificano la composizione corporea: sarcopenia e miosteatosi restano stime.
B64: Marcatori di infiammazione (PCR, AGP) | C64: Il referto applica al profilo marziale una correzione BRINDA che dipende dai reattanti di fase acuta, ma quei valori non compaiono. Senza di essi i fattori di aggiustamento restano dedotti, non verificati.
B65: Contenuto emoglobinico reticolocitario (Ret-He) | C65: E l'esame con cui la fonte stessa propone di rivalutare il quadro fra tre mesi. Direbbe se il ferro arriva davvero ai precursori, che e la domanda che il profilo marziale lascia aperta.
B66: Epcidina | C66: Spiegherebbe il blocco ipotizzato, ma non e dosabile nella routine: i metodi non sono armonizzati e mancano cut-off condivisi. Resta uno strumento di ricerca, quindi il meccanismo si deduce, non si legge (PMID 22306005).
B68: AVVERTENZA | C68: Il punteggio composito e una sintesi documentale costruita su pesi scelti dall'analista, non uno score clinico validato. Serve a rendere esplicito e discutibile un giudizio, non a sostituirlo. I pesi sono modificabili nella colonna 'Peso' del foglio 02 e nella colonna D della sezione B. Prima di usare i numeri, leggere il foglio '08 Controlli', che riporta per ogni valore pubblicato se si riproduce dai dati grezzi e con quale riserva.

Sheet 07 Scenari
A1: 07 - Scenari di intervento
A2: Le celle gialle sono le leve dello scenario; il resto e calcolato. I valori sono proiezioni sull'ordine di grandezza degli effetti riportati dagli studi, non risultati misurati.
B4: TAVOLA 1 - Leve cardiovascolari
B5: Scenario | C5: FC (bpm) | D5: SV (mL) | E5: SBP (mmHg) | F5: MAP (mmHg) | G5: CO (L/min) | H5: MSI | I5: RPP (bpm*mmHg) | J5: Battiti extra /anno | K5: RR mort.tot. | L5: Commento
A6: 1 | B6: Situazione attuale | C6: 82 | D6: 66 | E6: 128 | F6: ='01 Input'!$B$22+0.4*(E6-'01 Input'!$B$22) -> 101.6 | G6: =D6*C6/1000 -> 5.412 | H6: =C6/F6 -> 0.80708661 | I6: =C6*E6 -> 10496 | J6: =MAX(0,C6-'01 Input'!$B$67)*60*24*365 -> 3153600 | K6: =1.09^((C6-'01 Input'!$B$65)/10) -> 1.1577773 | L6: Quindici indici cardiologici su sedici stampati come normali.
A7: 2 | B7: Esercizio supervisionato, 3 mesi | C7: 72 | D7: 66 | E7: 124 | F7: ='01 Input'!$B$22+0.4*(E7-'01 Input'!$B$22) -> 100 | G7: =D7*C7/1000 -> 4.752 | H7: =C7/F7 -> 0.72 | I7: =C7*E7 -> 8928 | J7: =MAX(0,C7-'01 Input'!$B$67)*60*24*365 -> 0 | K7: =1.09^((C7-'01 Input'!$B$65)/10) -> 1.062181 | L7: PMID 15793048: -19% sul prodotto cardiovascolare. Nel gruppo non supervisionato il valore era rimasto invariato.
A8: 3 | B8: Cessazione del fumo, oltre 4 settimane | C8: 77 | D8: 66 | E8: 126 | F8: ='01 Input'!$B$22+0.4*(E8-'01 Input'!$B$22) -> 100.8 | G8: =D8*C8/1000 -> 5.082 | H8: =C8/F8 -> 0.76388889 | I8: =C8*E8 -> 9702 | J8: =MAX(0,C8-'01 Input'!$B$67)*60*24*365 -> 525600 | K8: =1.09^((C8-'01 Input'!$B$65)/10) -> 1.1089496 | L8: PMID 8651120: la FC cala e la variabilita migliora, ma a 4 settimane resta sopra i valori attesi per l'eta.
A9: 4 | B9: Esercizio + cessazione | C9: 70 | D9: 70 | E9: 122 | F9: ='01 Input'!$B$22+0.4*(E9-'01 Input'!$B$22) -> 99.2 | G9: =D9*C9/1000 -> 4.9 | H9: =C9/F9 -> 0.70564516 | I9: =C9*E9 -> 8540 | J9: =MAX(0,C9-'01 Input'!$B$67)*60*24*365 -> 0 | K9: =1.09^((C9-'01 Input'!$B$65)/10) -> 1.0440307 | L9: Le due leve insieme, con recupero parziale di gittata dovuto al condizionamento.
A10: 5 | B10: Pompa piu capiente a pari portata | C10: 68 | D10: 80 | E10: 128 | F10: ='01 Input'!$B$22+0.4*(E10-'01 Input'!$B$22) -> 101.6 | G10: =D10*C10/1000 -> 5.44 | H10: =C10/F10 -> 0.66929134 | I10: =C10*E10 -> 8704 | J10: =MAX(0,C10-'01 Input'!$B$67)*60*24*365 -> 0 | K10: =1.09^((C10-'01 Input'!$B$65)/10) -> 1.0261904 | L10: Stessa portata ottenuta con gittata nel medio dell'intervallo: il confronto che mostra cosa nasconde una portata normale.
A11: 6 | B11: Obiettivo fascia di minimo rischio | C11: 65 | D11: 80 | E11: 120 | F11: ='01 Input'!$B$22+0.4*(E11-'01 Input'!$B$22) -> 98.4 | G11: =D11*C11/1000 -> 5.2 | H11: =C11/F11 -> 0.66056911 | I11: =C11*E11 -> 7800 | J11: =MAX(0,C11-'01 Input'!$B$67)*60*24*365 -> 0 | K11: =1.09^((C11-'01 Input'!$B$65)/10) -> 1 | L11: Frequenza nella fascia 60-69 bpm, minimo di mortalita secondo PMID 11337213.
B13: TAVOLA 2 - Leve antropometriche
B14: Scenario | C14: Peso (kg) | D14: Vita (cm) | E14: Fianchi (cm) | F14: BMI | G14: WHtR | H14: Conicity | I14: LAP | J14: CMI | K14: VAI | L14: Commento
A15: 1 | B15: Situazione attuale | C15: 74 | D15: 97 | E15: 100 | F15: =C15/('01 Input'!$B$12/100)^2 -> 24.441802 | G15: =D15/'01 Input'!$B$12 -> 0.55747126 | H15: =(D15/100)/(0.109*SQRT(C15/('01 Input'!$B$12/100))) -> 1.3645957 | I15: =(D15-65)*('01 Input'!$B$30/88.57) -> 53.47183 | J15: =(D15/'01 Input'!$B$12)*(('01 Input'!$B$30/88.57)/('01 Input'!$B$29/38.67)) -> 0.87859327 | K15: =(D15/(39.68+1.88*F15))*(('01 Input'!$B$30/88.57)/1.03)*(1.31/('01 Input'!$B$29/38.67)) -> 2.2706085 | L15: BMI normale, sei indici di forma e ibridi oltre soglia.
A16: 2 | B16: -5 cm di vita a pari peso | C16: 74 | D16: 92 | E16: 99 | F16: =C16/('01 Input'!$B$12/100)^2 -> 24.441802 | G16: =D16/'01 Input'!$B$12 -> 0.52873563 | H16: =(D16/100)/(0.109*SQRT(C16/('01 Input'!$B$12/100))) -> 1.2942557 | I16: =(D16-65)*('01 Input'!$B$30/88.57) -> 45.116857 | J16: =(D16/'01 Input'!$B$12)*(('01 Input'!$B$30/88.57)/('01 Input'!$B$29/38.67)) -> 0.83330496 | K16: =(D16/(39.68+1.88*F16))*(('01 Input'!$B$30/88.57)/1.03)*(1.31/('01 Input'!$B$29/38.67)) -> 2.1535669 | L16: Ricomposizione senza calo ponderale: e cio che l'esercizio contro resistenza produce per primo.
A17: 3 | B17: -3 kg con -6 cm di vita | C17: 71 | D17: 91 | E17: 98 | F17: =C17/('01 Input'!$B$12/100)^2 -> 23.450918 | G17: =D17/'01 Input'!$B$12 -> 0.52298851 | H17: =(D17/100)/(0.109*SQRT(C17/('01 Input'!$B$12/100))) -> 1.3069541 | I17: =(D17-65)*('01 Input'!$B$30/88.57) -> 43.445862 | J17: =(D17/'01 Input'!$B$12)*(('01 Input'!$B$30/88.57)/('01 Input'!$B$29/38.67)) -> 0.82424729 | K17: =(D17/(39.68+1.88*F17))*(('01 Input'!$B$30/88.57)/1.03)*(1.31/('01 Input'!$B$29/38.67)) -> 2.1775299 | L17: Rientro nella forbice del peso desiderabile (68-71 kg secondo Lorenz e Creff).
A18: 4 | B18: Vita sotto meta altezza (WHtR 0,50) | C18: 71 | D18: 87 | E18: 97 | F18: =C18/('01 Input'!$B$12/100)^2 -> 23.450918 | G18: =D18/'01 Input'!$B$12 -> 0.5 | H18: =(D18/100)/(0.109*SQRT(C18/('01 Input'!$B$12/100))) -> 1.2495056 | I18: =(D18-65)*('01 Input'!$B$30/88.57) -> 36.761883 | J18: =(D18/'01 Input'!$B$12)*(('01 Input'!$B$30/88.57)/('01 Input'!$B$29/38.67)) -> 0.78801664 | K18: =(D18/(39.68+1.88*F18))*(('01 Input'!$B$30/88.57)/1.03)*(1.31/('01 Input'!$B$29/38.67)) -> 2.0818143 | L18: Soglia della regola aurea: la vita misura meno della meta dell'altezza.
A19: 5 | B19: Obiettivo pieno su tutti gli indici di forma | C19: 69 | D19: 84 | E19: 96 | F19: =C19/('01 Input'!$B$12/100)^2 -> 22.790329 | G19: =D19/'01 Input'!$B$12 -> 0.48275862 | H19: =(D19/100)/(0.109*SQRT(C19/('01 Input'!$B$12/100))) -> 1.2237786 | I19: =(D19-65)*('01 Input'!$B$30/88.57) -> 31.748899 | J19: =(D19/'01 Input'!$B$12)*(('01 Input'!$B$30/88.57)/('01 Input'!$B$29/38.67)) -> 0.76084366 | K19: =(D19/(39.68+1.88*F19))*(('01 Input'!$B$30/88.57)/1.03)*(1.31/('01 Input'!$B$29/38.67)) -> 2.0402759 | L19: Rientro sotto il cut-off di 0,52 per WHtR e sotto 1,25 per il Conicity Index.
B21: Nota: i cut-off da rientrare sono WHtR 0,52 - Conicity 1,25 - LAP 26,7 - CMI 0,39 - VAI 1,92. Gli indici ibridi migliorano anche solo riducendo la vita, perche la vita e il loro primo fattore.

Sheet 08 Controlli
A1: 08 - Controlli di riproducibilita
A2: Ogni valore pubblicato dalle fonti e stato ricalcolato dai dati grezzi. Qui e registrato cosa torna e cosa no.
A4: # | B4: Fonte | C4: Elemento verificato | D4: Valore pubblicato | E4: Valore ricalcolato | F4: Esito | G4: Impatto sul giudizio
A5: 1 | B5: Art.2 | C5: BMI da peso e altezza | D5: 24,09 | E5: 24,44 | F5: Scostamento | G5: 74 kg su 174 cm danno 24,44. Per ottenere 24,09 servirebbero 72,9 kg a 174 cm, oppure 175,3 cm a 74 kg. Non e un arrotondamento: uno dei tre numeri pubblicati e incoerente con gli altri due. Il BMI entra nel VAI, nell'ABSI e nella correzione del polpaccio, quindi l'errore si propaga su tre indici.
A6: 2 | B6: Art.2 | C6: BMI usato internamente dal referto | D6: - | E6: 24,09 | F6: Dedotto | G6: Il VAI pubblicato (2,29) si riproduce solo con BMI 24,09; con 24,44 si otterrebbe 2,27. Il referto usa dunque internamente il BMI dichiarato, non quello ricavabile da peso e altezza. Il modello mantiene entrambi i valori senza sceglierne uno.
A7: 3 | B7: Art.2 | C7: Abdominal Volume Index | D7: 11,89 | E7: 18,82 | F7: Non riproducibile | G7: Scostamento del 58%. La formula standard (2 x vita^2 + 0,7 x (vita-fianchi)^2)/1000 non restituisce il valore pubblicato, e non e stata trovata alcuna variante che lo faccia. L'esito qualitativo non cambia: l'indice resta dentro il riferimento con entrambi i valori.
A8: 4 | B8: Art.2 | C8: Percentuale di grasso corporeo | D8: 23% | E8: 24,6% (Deurenberg) | F8: Non riproducibile | G8: La formula non e dichiarata. Deurenberg e la candidata piu probabile ma restituisce 24,6% con il BMI ricalcolato e 24,2% con quello del referto. Scostamento di circa 1,2 punti. Poco rilevante: e comunque una stima derivata dal BMI.
A9: 5 | B9: Art.2 | C9: Circonferenza polpaccio corretta per BMI | D9: 33,5 cm | E9: 34,0 cm | F9: Non riproducibile | G9: IMPATTO ALTO. La correzione categoriale del consenso EWGSOP2 non prevede aggiustamenti per BMI fra 18,5 e 24,9, quindi il valore resterebbe 34,0 cm, cioe esattamente sulla soglia invece che sotto. La diagnosi di sarcopenia moderata dipende interamente da una correzione di 5 millimetri la cui formula non e pubblicata.
A10: 6 | B10: Art.2 | C10: Conteggio degli indici oltre soglia | D10: 6 su 12 | E10: 9 su 12 | F10: Scostamento | G10: Applicando i cut-off riportati dalle tabelle della fonte stessa risultano oltre soglia: vita/altezza, vita/fianchi, conicita, BAI, LAP, CMI, VAI, ABSI e polpaccio. Restano dentro solo percentuale di grasso, BRI e AVI. La direzione della conclusione non cambia, anzi si rafforza.
A11: 7 | B11: Art.2 | C11: ABSI z-score | D11: 1,52 | E11: non ricalcolabile | F11: Non verificabile | G11: Il valore grezzo di ABSI si ricalcola (0,0873), ma lo z-score richiede le tabelle NHANES per eta e sesso, che la fonte non riporta. Nel foglio 02 il valore viene inserito a mano e non e verificato.
A12: 8 | B12: Art.1 | C12: Numero di indici cardiologici | D12: 16 | E12: 15 tabulati | F12: Scostamento | G12: La fonte dichiara sedici indici ma le tre tabelle ne contengono quindici. Il modello include la superficie corporea come sedicesima riga informativa, essendo l'unico altro valore numerico del referto citato nel testo.
A13: 9 | B13: Art.1 | C13: Pressione arteriosa media | D13: 101 mmHg | E13: 98,7 (classica) / 101,6 (DBP+0,4xPP) | F13: Formula ricostruita | G13: La formula classica non riproduce il valore pubblicato. Rilevante perche la MAP e il denominatore del Modified Shock Index: con la formula classica il MSI passerebbe da 0,81 a 0,83.
A14: 10 | B14: Art.1 | C14: Left Cardiac Work Index | D14: 627 mW/m2 | E14: 639 mW/m2 | F14: Scostamento minore | G14: Circa il 2,6%, interamente dovuto agli arrotondamenti a monte: usando il Cardiac Index arrotondato a 2,8 e la MAP a 101 si ottengono 628. Nessun impatto sul giudizio.
A15: 11 | B15: Art.1 | C15: Resistenze vascolari sistemiche | D15: 2,7 kU*m2 | E15: 2,70 con CVP assunta a 5 mmHg | F15: Riproducibile con assunzione | G15: La pressione venosa centrale non e pubblicata. Con CVP 5 mmHg il calcolo coincide, con CVP 0 si otterrebbe 2,8, che spingerebbe l'indice sopra il limite superiore di 2,8. L'assunzione e quindi tutt'altro che neutra.
A16: 12 | B16: Art.1 | C16: Indice di rigidita arteriosa | D16: 0,44 | E16: 0,436 (PP/MAP) | F16: Formula ricostruita | G16: Riproduce il valore pubblicato. Il rapporto alternativo PP/SBP darebbe 0,34.
... A29: 25 | B29: Entrambe | C29: Tutti gli altri indici | D29: - | E29: coincidono | F29: Riproducibile | G29: Riproducono il valore pubblicato entro l'arrotondamento: pressione di pulsazione, riserva, Modified Shock Index, prodotto cardiovascolare, portata, Cardiac Index, morfotipo, pesi ideali di Lorenz e Creff, vita/altezza, vita/fianchi, Conicity Index, BAI, BRI, LAP, CMI e VAI.
C31: Sintesi
C32: Elementi verificati | E32: =COUNTA(C5:C29) -> 25
C33: Riproducibili senza riserve | E33: =COUNTIF(F5:F29,"Riproducibile") -> 5
C34: Ricostruiti o dipendenti da assunzioni dell'analista | E34: =COUNTIF(F5:F29,"Formula ricostruita")+COUNTIF(F5:F29,"Riproducibile con assunzione")+COUNTIF(F5:F29,"Dedotto")+COUNTIF(F5:F29,"Sensibile alle unita")+COUNTIF(F5:F29,"Sottodeterminato") -> 8
C35: Scostamenti, valori non riproducibili o incongruenze | E35: =E32-E33-E34 -> 12
C37: Come leggere questo foglio
C38: Nessuno di questi scostamenti ribalta le conclusioni delle fonti: gli indici che segnalano rischio lo segnalano con entrambi i valori, e il conteggio degli indici oltre soglia risulta piu alto del dichiarato, non piu basso. Due elementi meritano pero attenzione. Il primo e la diagnosi di sarcopenia, che poggia su una correzione di cinque millimetri la cui formula non e pubblicata e che con il criterio del consenso europeo non verrebbe applicata. Il secondo e il BMI, che non discende dal peso e dall'altezza dichiarati e che alimenta tre indici derivati. Entrambi si risolvono chiedendo alla fonte i dati grezzi o la formula usata.

Sheet 09 Conversioni
A1: 09 - Profilo marziale in unita convenzionali
A2: Il referto usa unita SI, che quasi nessun laboratorio italiano stampa. Qui gli stessi valori nelle unita di un referto ordinario.
A4: # | B4: Analita | C4: Valore SI | D4: Unita SI | E4: Fattore | F4: Valore convenzionale | G4: Unita | H4: Nota
A5: 1 | B5: Sideremia | C5: ='02 Indici'!$E$37 -> 13.6 | D5: uM | E5: 5.585 | F5: =C5*E5 -> 75.956 | G5: ug/dL | H5: Il valore convenzionale corrispondente e appena sopra il limite inferiore tipico per l'uomo adulto.
A6: 2 | B6: Sideremia aggiustata | C6: ='02 Indici'!$E$38 -> 17.10064 | D6: uM | E6: 5.585 | F6: =C6*E6 -> 95.507074 | G6: ug/dL
A7: 3 | B7: Transferrina | C7: ='02 Indici'!$E$39 -> 39.2 | D7: uM | E7: 7.957 | F7: =C7*E7 -> 311.9144 | G7: mg/dL | H7: Convertita con peso molecolare 79.570 g/mol.
A8: 4 | B8: TIBC | C8: ='02 Indici'!$E$40 -> 78.4 | D8: uM | E8: 5.585 | F8: =C8*E8 -> 437.864 | G8: ug/dL | H8: Il valore convenzionale e sopra l'intervallo tipico: molti posti liberi sui camion.
A9: 5 | B9: UIBC | C9: ='02 Indici'!$E$41 -> 64.8 | D9: uM | E9: 5.585 | F9: =C9*E9 -> 361.908 | G9: ug/dL
A10: 6 | B10: Ferritina | C10: ='02 Indici'!$E$44 -> 160.9 | D10: pM | E10: 0.45 | F10: =C10*E10 -> 72.405 | G10: ug/L (ng/mL) | H10: Convertita con peso molecolare 450.000 g/mol. Nelle unita di un referto ordinario e un valore che nessuno segnalerebbe.
A11: 7 | B11: Ferritina aggiustata | C11: ='02 Indici'!$E$45 -> 120.70718 | D11: pM | E11: 0.45 | F11: =C11*E11 -> 54.318231 | G11: ug/L (ng/mL) | H11: Sotto la soglia di 30 ug/L nessuno discuterebbe la carenza; qui il valore resta sopra, ed e per questo che il caso e difficile.
A12: 8 | B12: Soglia ottimale di ferritina aggiustata | C12: =283.1 -> 283.1 | D12: pM | E12: 0.45 | F12: =C12*E12 -> 127.395 | G12: ug/L (ng/mL) | H12: Il riferimento ottimale del referto tradotto in unita convenzionali.
B14: Perche questo foglio esiste
B15: I fattori di conversione della ferritina e della transferrina dipendono dal peso molecolare, che non e una costante universale: la ferritina e riportata in letteratura fra 440.000 e 474.000 g/mol a seconda della composizione in catene leggere e pesanti. E la ragione per cui il rapporto transferrina/log(ferritina) del foglio 02 non coincide al centesimo con quello pubblicato. Per sideremia, TIBC e UIBC il fattore 5,585 e invece esatto, essendo il peso atomico del ferro diviso dieci.
